{
  "ACCELERANT_POWER.description": "[gold]중독[/gold]이 1번 추가로 발동합니다.",
  "ACCELERANT_POWER.smartDescription": "[gold]중독[/gold]이 [blue]{Amount}[/blue]번 추가로 발동합니다.",
  "ACCELERANT_POWER.title": "촉진제",
  "ACCURACY_POWER.description": "[gold]단도[/gold]의 피해량이 증가합니다.",
  "ACCURACY_POWER.smartDescription": "[gold]단도[/gold]의 피해량이 [blue]{Amount}[/blue] 증가합니다.",
  "ACCURACY_POWER.title": "정밀",
  "ADAPTABLE_POWER.description": "이 생물은 처치될 시 더 강력한 모습으로 부활합니다.",
  "ADAPTABLE_POWER.smartDescription": "[gold]{OwnerName}[/gold](은)는 처치될 시 더 강력한 모습으로 부활합니다.",
  "ADAPTABLE_POWER.title": "적응력",
  "ADAPTATION_POWER.description": "[gold]방어도[/gold]를 얻을 때마다, 이번 턴 동안 [gold]민첩[/gold]을 [blue]3[/blue] 얻습니다.",
  "ADAPTATION_POWER.smartDescription": "[gold]방어도[/gold]를 얻을 때마다, 이번 턴 동안 [gold]민첩[/gold]을 [blue]{Amount}[/blue] 얻습니다.",
  "ADAPTATION_POWER.title": "적응",
  "AFTERIMAGE_POWER.description": "카드를 사용할 때마다, [gold]방어도[/gold]를 [blue]1[/blue] 얻습니다.",
  "AFTERIMAGE_POWER.smartDescription": "카드를 사용할 때마다, [gold]방어도[/gold]를 [blue]{Amount}[/blue] 얻습니다.",
  "AFTERIMAGE_POWER.title": "잔상",
  "AGGRESSION_POWER.description": "내 턴 시작 시, [gold]버린 카드 더미[/gold]에서 무작위 공격 카드를 1장 [gold]손[/gold]으로 가져오고 남은 전투 동안 [gold]강화[/gold]합니다.",
  "AGGRESSION_POWER.smartDescription": "내 턴 시작 시, [gold]버린 카드 더미[/gold]에서 무작위 공격 카드를 [blue]{Amount}[/blue]장 [gold]손[/gold]으로 가져오고 남은 전투 동안 [gold]강화[/gold]합니다.",
  "AGGRESSION_POWER.title": "공격성",
  "AMBERGRIS_POWER.description": "이번 턴 후에 추가 턴을 진행합니다.",
  "AMBERGRIS_POWER.title": "용연향",
  "ARSENAL_POWER.description": "카드를 생성할 때마다, [gold]힘[/gold]을 [blue]1[/blue] 얻습니다.",
  "ARSENAL_POWER.smartDescription": "카드를 생성할 때마다, [gold]힘[/gold]을 [blue]{Amount}[/blue] 얻습니다.",
  "ARSENAL_POWER.title": "무기고",
  "ARTIFACT_POWER.description": "해로운 효과를 [gold]무효화[/gold]합니다.",
  "ARTIFACT_POWER.smartDescription": "해로운 효과를 [blue]{Amount}[/blue]번 [gold]무효화[/gold]합니다.",
  "ARTIFACT_POWER.title": "인공물",
  "ASLEEP_POWER.description": "TODO",
  "ASLEEP_POWER.smartDescription": "체력을 잃거나 {Amount:choose(1):다음 턴 시작 시|[blue]{}[/blue]턴 경과 시} 깨어납니다.",
  "ASLEEP_POWER.title": "수면",
  "AUTOMATION_POWER.description": "카드를 [blue]10[/blue]장 뽑을 때마다, [gold]에너지[/gold]를 얻습니다.",
  "AUTOMATION_POWER.smartDescription": "카드를 [blue]{BaseCards}[/blue]장 뽑을 때마다, {Amount:energyIcons()}를 얻습니다.",
  "AUTOMATION_POWER.title": "자동화",
  "A_THOUSAND_CUTS_POWER.description": "카드를 사용할 때마다, 모든 적에게 피해를 [blue]1[/blue] 줍니다.",
  "A_THOUSAND_CUTS_POWER.smartDescription": "카드를 사용할 때마다, 모든 적에게 피해를 [blue]{Amount}[/blue] 줍니다.",
  "A_THOUSAND_CUTS_POWER.title": "능지처참",
  "BACK_ATTACK_LEFT_POWER.description": "당신의 뒤쪽에서 공격 시 가하는 피해량이 [blue]50%[/blue] 증가합니다.",
  "BACK_ATTACK_LEFT_POWER.title": "후방 공격",
  "BACK_ATTACK_RIGHT_POWER.description": "당신의 뒤쪽에서 공격 시 가하는 피해량이 [blue]50%[/blue] 증가합니다.",
  "BACK_ATTACK_RIGHT_POWER.title": "후방 공격",
  "BARRICADE_POWER.description": "이 생물의 턴 시작 시 [gold]방어도[/gold]가 사라지지 않습니다.",
  "BARRICADE_POWER.smartDescription": "{ApplierName.StringValue:cond:[gold]{OwnerName}의 턴[/gold]|내 턴} 시작 시 [gold]방어도[/gold]가 사라지지 않습니다.",
  "BARRICADE_POWER.title": "바리케이드",
  "BATTLEWORN_DUMMY_TIME_LIMIT_POWER.description": "전투로 손상된 훈련 인형을 쓰러뜨릴 수 있는 턴이 [blue]3[/blue]턴 남았습니다.",
  "BATTLEWORN_DUMMY_TIME_LIMIT_POWER.smartDescription": "전투로 손상된 훈련 인형을 쓰러뜨릴 수 있는 턴이 [blue]{Amount}[/blue]턴 남았습니다.",
  "BATTLEWORN_DUMMY_TIME_LIMIT_POWER.title": "시간 제한",
  "BEACON_OF_HOPE_POWER.description": "내 턴 동안 [gold]방어도[/gold]를 얻을 때마다, 다른 플레이어가 그 절반만큼 [gold]방어도[/gold]를 얻습니다.",
  "BEACON_OF_HOPE_POWER.smartDescription": "내 턴 동안 [gold]방어도[/gold]를 얻을 때마다, 다른 플레이어가 그 절반만큼 [gold]방어도[/gold]를 얻습니다.",
  "BEACON_OF_HOPE_POWER.title": "희망의 등불",
  "BIASED_COGNITION_POWER.description": "내 턴 시작 시, [gold]밀집[/gold]을 [blue]1[/blue] 잃습니다.",
  "BIASED_COGNITION_POWER.smartDescription": "내 턴 시작 시, [gold]밀집[/gold]을 [blue]{Amount}[/blue] 잃습니다.",
  "BIASED_COGNITION_POWER.title": "인지 편향",
  "BLACK_HOLE_POWER.description": "{singleStarIcon}을 소모하거나 얻을 때마다, 모든 적에게 피해를 [blue]3[/blue] 줍니다.",
  "BLACK_HOLE_POWER.smartDescription": "{singleStarIcon}을 소모하거나 얻을 때마다, 모든 적에게 피해를 [blue]{Amount}[/blue] 줍니다.",
  "BLACK_HOLE_POWER.title": "블랙홀",
  "BLOCK_NEXT_TURN_POWER.description": "다음 턴 시작 시, [gold]방어도[/gold]를 [blue]4[/blue] 얻습니다.",
  "BLOCK_NEXT_TURN_POWER.smartDescription": "다음 턴 시작 시, [gold]방어도[/gold]를 [blue]{Amount}[/blue] 얻습니다.",
  "BLOCK_NEXT_TURN_POWER.title": "다음 턴 방어도",
  "BLUR_POWER.description": "다음 턴 시작 시 [gold]방어도[/gold]가 사라지지 않습니다.",
  "BLUR_POWER.smartDescription": "{Amount:choose(1):|{}턴 동안,} 내 턴 시작 시 [gold]방어도[/gold]가 사라지지 않습니다.",
  "BLUR_POWER.title": "흐릿함",
  "BORROWED_TIME_POWER.description": "이번 턴 동안 카드의 비용이 1 증가합니다.",
  "BORROWED_TIME_POWER.smartDescription": "이번 턴 동안 카드의 비용이 {Amount:energyIcons()} 증가합니다.",
  "BORROWED_TIME_POWER.title": "연명",
  "BUFFER_POWER.description": "다음에 체력을 잃는 것을 막아줍니다.",
  "BUFFER_POWER.smartDescription": "다음에 체력을 잃는 것을{Amount:choose(1):| [blue]{}[/blue]번} 막아줍니다.",
  "BUFFER_POWER.title": "버퍼",
  "BURROWED_POWER.description": "이 생물의 턴 시작 시 [gold]방어도[/gold]가 사라지지 않습니다. 모든 [gold]방어도[/gold]가 사라질 시 대상이 [gold]기절[/gold] 상태가 됩니다.",
  "BURROWED_POWER.smartDescription": "[gold]{OwnerName}[/gold]의 턴 시작 시 [gold]방어도[/gold]가 사라지지 않습니다. 모든 [gold]방어도[/gold]가 사라질 시 대상이 [gold]기절[/gold] 상태가 됩니다.",
  "BURROWED_POWER.title": "잠복",
  "BURST_POWER.description": "이번 턴에 다음에 사용하는 스킬 카드가 추가로 사용됩니다.",
  "BURST_POWER.smartDescription": "이번 턴에 다음에 사용하는 {Amount:choose(1):스킬 카드가|스킬 카드 [blue]{}[/blue]장이} 추가로 사용됩니다.",
  "BURST_POWER.title": "폭주",
  "CACOPHONY_POWER.description": "모든 플레이어가 뽑는 카드 33장마다, 무작위 적에게 피해를 줍니다.",
  "CACOPHONY_POWER.smartDescription": "{Cards:choose(1):아무 플레이어가|모든 플레이어가} 카드를 [blue]{Cards}[/blue]장 뽑은 뒤, 무작위 적에게 피해를 [blue]{Amount}[/blue] 줍니다.",
  "CACOPHONY_POWER.title": "불협화음",
  "CALAMITY_POWER.description": "공격 카드를 사용할 때마다, 무작위 공격 카드를 1장 [gold]손[/gold]으로 가져옵니다.",
  "CALAMITY_POWER.smartDescription": "공격 카드를 사용할 때마다, 무작위 공격 카드를 {Amount:choose(1):1장|[blue]{}[/blue]장} [gold]손[/gold]으로 가져옵니다.",
  "CALAMITY_POWER.title": "재앙",
  "CALCIFY_POWER.description": "[gold]골골이[/gold]가 가하는 공격의 피해량이 증가합니다.",
  "CALCIFY_POWER.smartDescription": "[gold]골골이[/gold]가 가하는 공격의 피해량이 [blue]{Amount}[/blue] 증가합니다.",
  "CALCIFY_POWER.title": "석회화",
  "CALL_OF_THE_VOID_POWER.description": "내 턴 시작 시, 무작위 카드를 [blue]1[/blue]장 [gold]손[/gold]으로 가져옵니다. 그 카드가 [gold]휘발성[/gold]을 얻습니다.",
  "CALL_OF_THE_VOID_POWER.smartDescription": "내 턴 시작 시, 무작위 카드를 [blue]{Amount}[/blue]장 [gold]손[/gold]으로 가져옵니다. 그 카드가 [gold]휘발성[/gold]을 얻습니다.",
  "CALL_OF_THE_VOID_POWER.title": "공허의 부름",
  "CHAINS_OF_BINDING_POWER.description": "매 턴마다 처음으로 뽑는 카드 [blue]3[/blue]장에 [gold]구속[/gold]의 고난이 부여됩니다.",
  "CHAINS_OF_BINDING_POWER.smartDescription": "매 턴마다 처음으로 뽑는 카드 [blue]{Amount}[/blue]장에 [gold]구속[/gold]의 고난이 부여됩니다.",
  "CHAINS_OF_BINDING_POWER.title": "속박의 사슬",
  "CHILD_OF_THE_STARS_POWER.description": "소모한 {singleStarIcon}당 [gold]방어도[/gold]를 [blue]1[/blue] 얻습니다.",
  "CHILD_OF_THE_STARS_POWER.smartDescription": "소모한 {singleStarIcon}당 [gold]방어도[/gold]를 [blue]{Amount}[/blue] 얻습니다.",
  "CHILD_OF_THE_STARS_POWER.title": "별의 아이",
  "CLARITY_POWER.description": "다음 턴 시작 시, 카드를 추가로 [blue]1[/blue]장 뽑습니다.",
  "CLARITY_POWER.smartDescription": "다음 {Amount:choose(1):턴|[blue]{}[/blue]턴 동안 턴} 시작 시, 카드를 추가로 [blue]1[/blue]장 뽑습니다.",
  "CLARITY_POWER.title": "명확성",
  "COLOSSUS_POWER.description": "이번 턴에 [gold]취약[/gold] 상태의 적에게서 받는 피해량이 [blue]50%[/blue] 감소합니다.",
  "COLOSSUS_POWER.smartDescription": "{Amount:choose(1):이번 턴에|[blue]{}[/blue] 턴 동안,} [gold]취약[/gold] 상태의 적에게서 받는 피해량이 [blue]{DamageDecrease:percentLess()}%[/blue] 감소합니다.",
  "COLOSSUS_POWER.title": "거상",
  "CONCOCT_POWER.description": "이번 턴 동안 막히지 않은 공격 피해를 줄 때마다, [gold]중독[/gold]을 [blue]3[/blue] 부여합니다.",
  "CONCOCT_POWER.smartDescription": "이번 턴 동안 막히지 않은 공격 피해를 줄 때마다, [gold]중독[/gold]을 [blue]{Amount}[/blue] 부여합니다.",
  "CONCOCT_POWER.title": "조제",
  "CONFUSED_POWER.description": "카드를 뽑을 때마다 카드의 비용이 [blue]0[/blue]부터 [blue]3[/blue]의 무작위 값으로 설정됩니다.",
  "CONFUSED_POWER.smartDescription": "카드를 뽑을 때마다 카드의 비용이 [blue]0[/blue]부터 [blue]3[/blue]의 무작위 값으로 설정됩니다.",
  "CONFUSED_POWER.title": "혼란",
  "CONQUEROR_POWER.description": "이번 턴 동안 대상 적이 [gold]군주의 칼날[/gold]로 받는 피해량이 2배가 됩니다.",
  "CONQUEROR_POWER.smartDescription": "{Amount:choose(1):이번 턴 동안|다음 [blue]{}[/blue]턴 동안} [gold]{OwnerName}[/gold](이)가 [gold]군주의 칼날[/gold]로 받는 피해량이 2배가 됩니다.",
  "CONQUEROR_POWER.title": "정복자",
  "CONSTRICT_POWER.description": "미끈거리는 교살마가 살아있는 동안, 턴 종료 시 피해를 [blue]1[/blue] 받습니다.",
  "CONSTRICT_POWER.smartDescription": "미끈거리는 교살마가 살아있는 동안, 턴 종료 시 피해를 [blue]{Amount}[/blue] 받습니다.",
  "CONSTRICT_POWER.title": "조이기",
  "CONSUMING_SHADOW_POWER.description": "내 턴 종료 시, 가장 왼쪽의 구체를 [gold]발현[/gold]합니다.",
  "CONSUMING_SHADOW_POWER.smartDescription": "내 턴 종료 시, 가장 왼쪽의 구체를{Amount:choose(1):| [blue]{}[/blue]번} [gold]발현[/gold]합니다.",
  "CONSUMING_SHADOW_POWER.title": "그림자 소모",
  "CONTRACTILITY_POWER.description": "다음 턴에, [gold]방어도[/gold]를 [blue]0[/blue] 얻습니다.",
  "CONTRACTILITY_POWER.smartDescription": "다음 턴에, [gold]방어도[/gold]를 [blue]{Amount}[/blue] 얻습니다.",
  "CONTRACTILITY_POWER.title": "신축성",
  "COOLANT_POWER.description": "내 턴 시작 시, 영창된 구체의 종류 하나당 [gold]방어도[/gold]를 [blue]3[/blue] 얻습니다.",
  "COOLANT_POWER.smartDescription": "내 턴 시작 시, 영창된 구체의 종류 하나당 [gold]방어도[/gold]를 [blue]{Amount}[/blue] 얻습니다.",
  "COOLANT_POWER.title": "냉각재",
  "CORROSIVE_WAVE_POWER.description": "이번 턴에 카드를 뽑을 때마다, 모든 적에게 [gold]중독[/gold]을 [blue]2[/blue] 부여합니다.",
  "CORROSIVE_WAVE_POWER.smartDescription": "이번 턴에 카드를 뽑을 때마다, 모든 적에게 [gold]중독[/gold]을 [blue]{Amount}[/blue] 부여합니다.",
  "CORROSIVE_WAVE_POWER.title": "부식성 파도",
  "CORRUPTION_POWER.description": "스킬 카드의 비용이 [blue]0[/blue]이 됩니다.\n스킬 카드를 사용할 때마다 그 카드를 [gold]소멸[/gold]시킵니다.",
  "CORRUPTION_POWER.title": "타락",
  "COUNTDOWN_POWER.description": "내 턴 시작 시, 무작위 적에게 [gold]종말[/gold]을 [blue]6[/blue] 부여합니다.",
  "COUNTDOWN_POWER.smartDescription": "내 턴 시작 시, 무작위 적에게 [gold]종말[/gold]을 [blue]{Amount}[/blue] 부여합니다.",
  "COUNTDOWN_POWER.title": "카운트다운",
  "COVERED_POWER.description": "아군의 엄호를 받습니다. 당신에게 가해지는 모든 공격이 대상 아군에게 옮겨집니다.",
  "COVERED_POWER.smartDescription": "[gold]{Applier}[/gold]의 엄호를 받습니다. 당신에게 가해지는 모든 공격이 대상 아군에게 옮겨집니다.",
  "COVERED_POWER.title": "엄호",
  "CRAB_RAGE_POWER.description": "아군이 죽을 시, 이 생물이 [gold]힘[/gold]을 [blue]5[/blue], [gold]방어도[/gold]를 [blue]99[/blue] 얻습니다.",
  "CRAB_RAGE_POWER.smartDescription": "아군이 죽을 시, [gold]{OwnerName}[/gold]이(가) [gold]힘[/gold]을 [blue]{StrengthPower}[/blue], [gold]방어도[/gold]를 [blue]{Block}[/blue] 얻습니다.",
  "CRAB_RAGE_POWER.title": "꽃게의 격노",
  "CREATIVE_AI_POWER.description": "내 턴 시작 시, 무작위 파워 카드를 1장 [gold]손[/gold]으로 가져옵니다.",
  "CREATIVE_AI_POWER.smartDescription": "내 턴 시작 시, 무작위 파워 카드를 {Amount:choose(1):1장|[blue]{}[/blue]장} [gold]손[/gold]으로 가져옵니다.",
  "CREATIVE_AI_POWER.title": "창의적인 인공지능",
  "CRIMSON_MANTLE_POWER.description": "내 턴 시작 시, 체력을 잃고 [gold]방어도[/gold]를 얻습니다.",
  "CRIMSON_MANTLE_POWER.smartDescription": "내 턴 시작 시, 체력을 [blue]{SelfDamage}[/blue] 잃고 [gold]방어도[/gold]를 [blue]{Amount}[/blue] 얻습니다.",
  "CRIMSON_MANTLE_POWER.title": "핏빛 망토",
  "CRUELTY_POWER.description": "취약 상태의 적이 받는 피해가 증가합니다.",
  "CRUELTY_POWER.smartDescription": "[gold]취약[/gold] 상태의 적이 받는 피해가 [blue]{Amount}%[/blue] 증가합니다.",
  "CRUELTY_POWER.title": "악랄함",
  "CURIOUS_POWER.description": "파워 카드의 비용이 [blue]1[/blue] {energyPrefix:energyIcons(1)} 감소합니다.",
  "CURIOUS_POWER.smartDescription": "파워 카드의 비용이 [blue]{Amount}[/blue] {energyPrefix:energyIcons(1)} 감소합니다.",
  "CURIOUS_POWER.title": "호기심",
  "CURL_UP_POWER.description": "피해를 입을 시, 몸을 말고 방어도를 얻습니다. (전투당 한 번)",
  "CURL_UP_POWER.smartDescription": "처음으로 공격을 적중당할 시, [gold]방어도[/gold]를 [blue]{Amount}[/blue] 얻습니다.",
  "CURL_UP_POWER.title": "몸 말기",
  "DAMPEN_POWER.banter": "너의 강화는 무용하다!!",
  "DAMPEN_POWER.description": "마법 기사가 살아있는 동안, 모든 카드가 [gold]열화[/gold]됩니다.",
  "DAMPEN_POWER.title": "위축",
  "DANSE_MACABRE_POWER.description": "에너지 비용이 [blue]2[/blue] 이상인 카드를 사용할 때마다, [gold]방어도[/gold]를 [blue]7[/blue] 얻습니다.",
  "DANSE_MACABRE_POWER.smartDescription": "비용이 {Energy:energyIcons()} 이상인 카드를 사용할 때마다, [gold]방어도[/gold]를 [blue]{Amount}[/blue] 얻습니다.",
  "DANSE_MACABRE_POWER.title": "죽음의 무도",
  "DARK_EMBRACE_POWER.description": "카드가 [gold]소멸[/gold]될 때마다, 카드를 [blue]1[/blue]장 뽑습니다.",
  "DARK_EMBRACE_POWER.smartDescription": "카드가 [gold]소멸[/gold]될 때마다, 카드를 [blue]{Amount}[/blue]장 뽑습니다.",
  "DARK_EMBRACE_POWER.title": "어둠의 포옹",
  "DEBILITATE_POWER.description": "다음 [blue]2[/blue]턴 동안 [gold]취약[/gold]과 [gold]약화[/gold]의 효과가 2배가 됩니다.",
  "DEBILITATE_POWER.smartDescription": "{Amount:choose(1):이번 턴에|다음 [blue]{}[/blue]턴 동안} [gold]취약[/gold]과 [gold]약화[/gold]의 효과가 2배가 됩니다.",
  "DEBILITATE_POWER.title": "쇠락",
  "DECREE_OF_ENTROPY_POWER.description": "내 턴 시작 시, 무작위 [gold]강화[/gold]된 카드를 [blue]1[/blue]장 손으로 가져옵니다.",
  "DECREE_OF_ENTROPY_POWER.smartDescription": "내 턴 시작 시, 무작위 [gold]강화[/gold]된 카드를 [blue]{Amount}[/blue]장 손으로 가져옵니다.",
  "DECREE_OF_ENTROPY_POWER.title": "예측 불허 판결",
  "DECREE_OF_UNMAKING_POWER.description": "적에게 피해를 줄 때마다, 대상 적에게 무작위 해로운 효과를 부여합니다.",
  "DECREE_OF_UNMAKING_POWER.smartDescription": "적에게 피해를 줄 때마다, 대상 적에게 무작위 해로운 효과를 [blue]{Amount}[/blue] 부여합니다.",
  "DECREE_OF_UNMAKING_POWER.title": "원상 복구 판결",
  "DEMESNE_POWER.description": "내 턴 시작 시, [gold]에너지[/gold]를 [blue]1[/blue] 얻고 카드를 추가로 [blue]1[/blue]장 뽑습니다.",
  "DEMESNE_POWER.smartDescription": "내 턴 시작 시, {Amount:energyIcons()}를 얻고 카드를 추가로 [blue]{Amount}[/blue]장 뽑습니다.",
  "DEMESNE_POWER.title": "권역",
  "DEMISE_POWER.description": "대상의 턴 종료 시, 이 생물이 체력을 X 잃습니다.",
  "DEMISE_POWER.smartDescription": "[gold]{OwnerName}[/gold]의 턴 종료 시, 대상이 체력을 [blue]{Amount}[/blue] 잃습니다.",
  "DEMISE_POWER.title": "종언",
  "DEMON_FORM_POWER.description": "내 턴 시작 시, [gold]힘[/gold]을 [blue]3[/blue] 얻습니다.",
  "DEMON_FORM_POWER.smartDescription": "내 턴 시작 시, [gold]힘[/gold]을 [blue]{Amount}[/blue] 얻습니다.",
  "DEMON_FORM_POWER.title": "악마의 형상",
  "DESPAIR_POWER.description": "부여하는 [gold]종말[/gold] [blue]1[/blue]마다, [gold]방어도[/gold]를 [blue]1[/blue] 얻습니다.",
  "DESPAIR_POWER.smartDescription": "부여하는 [gold]종말[/gold] [blue]1[/blue]마다, [gold]방어도[/gold]를 [blue]{Amount}[/blue] 얻습니다.",
  "DESPAIR_POWER.title": "절망",
  "DEVOUR_LIFE_POWER.description": "[gold]영혼[/gold]을 사용할 때마다, [gold]소환[/gold] [blue]1[/blue].",
  "DEVOUR_LIFE_POWER.smartDescription": "[gold]영혼[/gold]을 사용할 때마다, [gold]소환[/gold] [blue]{Amount}[/blue].",
  "DEVOUR_LIFE_POWER.title": "생명 삼키기",
  "DEXTERITY_DOWN_POWER.description": "이번 턴 종료 시, [gold]민첩[/gold]을 잃습니다.",
  "DEXTERITY_DOWN_POWER.smartDescription": "이번 턴 종료 시, [gold]민첩[/gold]을 [blue]{Amount}[/blue] 잃습니다.",
  "DEXTERITY_DOWN_POWER.title": "민첩 감소",
  "DEXTERITY_POWER.description": "민첩은 카드를 통해 얻는 [gold]방어도[/gold]를 증가시킵니다.",
  "DEXTERITY_POWER.smartDescription": "카드를 통해 얻는 [gold]방어도[/gold]가 [blue]{Amount:abs()}[/blue] {Amount:cond:<0?감소합니다|증가합니다}.",
  "DEXTERITY_POWER.title": "민첩",
  "DIE_FOR_YOU_POWER.description": "[gold]골골이[/gold]가 모든 막히지 않은 공격 피해를 받아냅니다.",
  "DIE_FOR_YOU_POWER.title": "살신성인",
  "DISINTEGRATION_POWER.description": "내 턴 종료 시, 피해를 [blue]5[/blue] 받습니다.",
  "DISINTEGRATION_POWER.smartDescription": "내 턴 종료 시, 피해를 [blue]{Amount}[/blue] 받습니다.",
  "DISINTEGRATION_POWER.title": "분해",
  "DOOM_POWER.description": "적의 턴 종료 시 적의 체력이 종말 이하라면, 사망합니다.",
  "DOOM_POWER.smartDescription": "{OnPlayer:플레이어의|적의} 턴 종료 시 [gold]{OwnerName}[/gold]의 체력이 [blue]{Amount}[/blue] 이하라면, 사망합니다.",
  "DOOM_POWER.title": "종말",
  "DOUBLE_DAMAGE_POWER.description": "이번 턴에 가하는 공격의 피해량이 2배가 됩니다.",
  "DOUBLE_DAMAGE_POWER.smartDescription": "{Amount:choose(1):이번 턴에|다음 [blue]{}[/blue]턴 동안,} 가하는 공격의 피해량이 2배가 됩니다.",
  "DOUBLE_DAMAGE_POWER.title": "2배의 피해",
  "DRAW_CARDS_NEXT_TURN_POWER.description": "다음 턴 시작 시, 카드를 추가로 [blue]1[/blue]장 뽑습니다.",
  "DRAW_CARDS_NEXT_TURN_POWER.smartDescription": "다음 턴 시작 시, 카드를 추가로 [blue]{Amount}[/blue]장 뽑습니다.",
  "DRAW_CARDS_NEXT_TURN_POWER.title": "다음 턴 카드 뽑기",
  "DUPLICATION_POWER.description": "다음에 사용하는 카드가 1번 추가로 사용됩니다.",
  "DUPLICATION_POWER.smartDescription": "다음에 사용하는 {Amount:choose(1):카드가|카드 [blue]{}[/blue]장이} 1번 추가로 사용됩니다.",
  "DUPLICATION_POWER.title": "복사",
  "ECHO_FORM_POWER.description": "매 턴마다 처음으로 사용하는 카드가 1번 추가로 사용됩니다.",
  "ECHO_FORM_POWER.smartDescription": "매 턴마다 처음으로 사용하는 {Amount:choose(1):카드가|카드 [blue]{}[/blue]장이} 1번 추가로 사용됩니다.",
  "ECHO_FORM_POWER.title": "메아리의 형상",
  "ENERGY_NEXT_TURN_POWER.description": "다음 턴에 [gold]에너지[/gold]를 추가로 얻습니다.",
  "ENERGY_NEXT_TURN_POWER.smartDescription": "다음 턴에 [blue]{Amount}[/blue] {energyPrefix:energyIcons(1)}를 추가로 얻습니다.",
  "ENERGY_NEXT_TURN_POWER.title": "다음 턴 에너지",
  "ENRAGE_POWER.description": "스킬 카드를 사용할 때마다, [gold]힘[/gold]을 [blue]2[/blue] 얻습니다.",
  "ENRAGE_POWER.smartDescription": "스킬 카드를 사용할 때마다, [gold]힘[/gold]을 [blue]{Amount}[/blue] 얻습니다.",
  "ENRAGE_POWER.title": "격분",
  "ENTROPY_POWER.description": "내 턴 시작 시, [gold]손[/gold]에 있는 카드를 [blue]1[/blue]장 [gold]변화[/gold]시킵니다.",
  "ENTROPY_POWER.smartDescription": "내 턴 시작 시, [gold]손[/gold]에 있는 카드를 [blue]{Amount}[/blue]장 [gold]변화[/gold]시킵니다.",
  "ENTROPY_POWER.title": "엔트로피",
  "ENVENOM_POWER.description": "막히지 않은 공격 피해를 줄 때마다, [gold]중독[/gold]을 [blue]1[/blue] 부여합니다.",
  "ENVENOM_POWER.smartDescription": "막히지 않은 공격 피해를 줄 때마다, [gold]중독[/gold]을 [blue]{Amount}[/blue] 부여합니다.",
  "ENVENOM_POWER.title": "독 바르기",
  "ESCAPE_ARTIST_POWER.description": "4턴 후에 전투를 떠납니다.",
  "ESCAPE_ARTIST_POWER.smartDescription": "{Amount:choose(1):이번 턴에|[blue]{}[/blue]턴 후에} 전투에서 탈출하려고합니다.",
  "ESCAPE_ARTIST_POWER.title": "탈출의 명수",
  "FAN_OF_KNIVES_POWER.description": "[gold]단도[/gold]가 모든 적을 대상으로 합니다.",
  "FAN_OF_KNIVES_POWER.title": "칼날 부채",
  "FASTEN_POWER.description": "수비 카드를 통해 얻는 [gold]방어도[/gold]가 [blue]4[/blue] 증가합니다.",
  "FASTEN_POWER.smartDescription": "수비 카드를 통해 얻는 [gold]방어도[/gold]가 [blue]{Amount}[/blue] 증가합니다.",
  "FASTEN_POWER.title": "고정시키기",
  "FEEL_NO_PAIN_POWER.description": "카드가 소멸될 때마다, [gold]방어도[/gold]를 [blue]3[/blue] 얻습니다.",
  "FEEL_NO_PAIN_POWER.smartDescription": "카드가 [gold]소멸[/gold]될 때마다, [gold]방어도[/gold]를 [blue]{Amount}[/blue] 얻습니다.",
  "FEEL_NO_PAIN_POWER.title": "무감각",
  "FERAL_POWER.description": "매 턴마다 처음 비용이 0{energyPrefix:energyIcons(1)}인 공격 카드를 사용 시, 그 카드를 [gold]손[/gold]으로 다시 가져옵니다.",
  "FERAL_POWER.smartDescription": "매 턴마다 처음 비용이 0{energyPrefix:energyIcons(1)}인 공격 카드를{Amount:choose(1):| [blue]{}[/blue]장} 사용 시, 그 카드를 [gold]손[/gold]으로 다시 가져옵니다.",
  "FERAL_POWER.title": "야성",
  "FLAME_BARRIER_POWER.description": "이번 턴에 공격을 받을 때마다, 공격한 적에게 피해를 [blue]4[/blue] 줍니다.",
  "FLAME_BARRIER_POWER.smartDescription": "이번 턴에 공격을 받을 때마다, 공격한 적에게 피해를 [blue]{Amount}[/blue] 줍니다.",
  "FLAME_BARRIER_POWER.title": "화염 장벽",
  "FLANKING_POWER.description": "이번 턴에 다른 아군이 이 적에게 가하는 공격 피해량이 [blue]2배[/blue]가 됩니다.",
  "FLANKING_POWER.remoteDescription": "[gold]{Applier}[/gold]로 인해 이번 턴에 내가 이 적에게 가하는 공격 피해량이 [blue]{Amount}[/blue]배가 됩니다.",
  "FLANKING_POWER.smartDescription": "이번 턴에 다른 아군이 이 적에게 가하는 공격 피해량이 [blue]{Amount}[/blue]배가 됩니다.",
  "FLANKING_POWER.title": "측면 공격",
  "FLUTTER_POWER.description": "공격 카드를 통해 받는 피해량이 [gold]50%[/gold] 감소합니다.",
  "FLUTTER_POWER.smartDescription": "공격 카드를 통해 받는 피해량이 [blue]{DamageDecrease}%[/blue] 감소합니다. 공격 피해를 [blue]{Amount}[/blue]번 받을 시 [gold]기절[/gold] 상태가 됩니다.",
  "FLUTTER_POWER.title": "날갯짓",
  "FOCUS_DOWN.description": "이번 턴 종료 시, [gold]밀집[/gold]을 [blue]1[/blue] 잃습니다.",
  "FOCUS_DOWN.smartDescription": "이번 턴 종료 시, [gold]밀집[/gold]을 [blue]{Amount}[/blue] 잃습니다.",
  "FOCUS_DOWN.title": "밀집 감소",
  "FOCUS_POWER.description": "구체들의 효율이 증가합니다.",
  "FOCUS_POWER.smartDescription": "구체들의 효율이 [blue]{Amount:abs()}[/blue] {Amount:cond:<0?감소합니다|증가합니다}.",
  "FOCUS_POWER.title": "밀집",
  "FORBIDDEN_GRIMOIRE_POWER.description": "전투 종료 시, [gold]덱[/gold]에서 카드를 1장 제거합니다.",
  "FORBIDDEN_GRIMOIRE_POWER.smartDescription": "전투 종료 시, [gold]덱[/gold]에서 카드를 [blue]{Amount}[/blue]장 제거합니다.",
  "FORBIDDEN_GRIMOIRE_POWER.title": "금지된 마도서",
  "FOREGONE_CONCLUSION_POWER.description": "다음 턴에, [gold]뽑을 카드 더미[/gold]에서 카드를 [blue]3[/blue]장 [gold]손[/gold]으로 가져옵니다.",
  "FOREGONE_CONCLUSION_POWER.selectionScreenPrompt": "손으로 가져올 카드를{Amount:choose(1):| {}장} 선택하세요.",
  "FOREGONE_CONCLUSION_POWER.smartDescription": "다음 턴에, [gold]뽑을 카드 더미[/gold]에서 카드를 [blue]{Amount}[/blue]장 [gold]손[/gold]으로 가져옵니다.",
  "FOREGONE_CONCLUSION_POWER.title": "필연적인 결과",
  "FRAIL_POWER.description": "손상 상태인 동안, 카드를 통해 얻는 [gold]방어도[/gold]가 [blue]25%[/blue] 감소합니다.",
  "FRAIL_POWER.smartDescription": "[blue]{Amount}[/blue]턴 동안 카드를 통해 얻는 [gold]방어도[/gold]가 [blue]25%[/blue] 감소합니다.",
  "FRAIL_POWER.title": "손상",
  "FREE_ATTACK_POWER.description": "다음에 사용하는 공격 카드의 비용이 [blue]0[/blue] {energyPrefix:energyIcons(1)}이 됩니다.",
  "FREE_ATTACK_POWER.smartDescription": "다음에 사용하는 {Amount:choose(1):공격 카드|공격 카드 [blue]{}[/blue]장}의 비용이 [blue]0[/blue] {energyPrefix:energyIcons(1)}이 됩니다.",
  "FREE_ATTACK_POWER.title": "무료 공격",
  "FREE_POWER_POWER.description": "다음에 사용하는 파워 카드의 비용이 [blue]0[/blue] {energyPrefix:energyIcons(1)}이 됩니다.",
  "FREE_POWER_POWER.smartDescription": "다음에 사용하는 {Amount:choose(1):파워 카드|파워 카드 [blue]{}[/blue]장}의 비용이 [blue]0[/blue] {energyPrefix:energyIcons(1)}이 됩니다.",
  "FREE_POWER_POWER.title": "무료 파워",
  "FREE_SKILL_POWER.description": "다음에 사용하는 스킬 카드의 비용이 [blue]0[/blue] {energyPrefix:energyIcons(1)}이 됩니다.",
  "FREE_SKILL_POWER.smartDescription": "다음에 사용하는 {Amount:choose(1):스킬 카드|스킬 카드 [blue]{}[/blue]장}의 비용이 [blue]0[/blue] {energyPrefix:energyIcons(1)}이 됩니다.",
  "FREE_SKILL_POWER.title": "무료 스킬",
  "FRIENDSHIP_POWER.description": "매 턴 시작 시, [gold]에너지[/gold]를 [blue]1[/blue] 얻습니다.",
  "FRIENDSHIP_POWER.smartDescription": "매 턴 시작 시, {Amount:energyIcons()}를 얻습니다.",
  "FRIENDSHIP_POWER.title": "우정",
  "FURNACE_POWER.description": "내 턴 시작 시, [gold]단조[/gold] [blue]5[/blue].",
  "FURNACE_POWER.smartDescription": "내 턴 시작 시, [gold]단조[/gold] [blue]{Amount}[/blue].",
  "FURNACE_POWER.title": "용광로",
  "GALVANIC_POWER.description": "파워 카드에 [gold]전기 자극[/gold]의 고난이 부여됩니다.",
  "GALVANIC_POWER.smartDescription": "파워 카드에 [gold]{AfflictionTitle}[/gold]의 고난이 부여됩니다.",
  "GALVANIC_POWER.title": "전류",
  "GENESIS_POWER.description": "내 턴 시작 시, {singleStarIcon}을 얻습니다.",
  "GENESIS_POWER.smartDescription": "내 턴 시작 시, {Amount:starIcons()}을 얻습니다.",
  "GENESIS_POWER.title": "창세",
  "GIGANTIFICATION_POWER.description": "다음에 사용하는 공격 카드의 피해량이 3배가 됩니다.",
  "GIGANTIFICATION_POWER.smartDescription": "다음에 사용하는 {Amount:choose(1):공격 카드|공격 카드 [blue]{}[/blue]장}의 피해량이 3배가 됩니다.",
  "GIGANTIFICATION_POWER.title": "거대화",
  "GOLDEN_PEARL.smartDescription": "처음으로 상인을 방문 시, 모든 상품의 가격이 [blue]75%[/blue] 할인됩니다.",
  "GRABBED.description": "이 생물을 처치 시, 빼앗긴 카드가 손으로 돌아옵니다.",
  "GRABBED.smartDescription": "[gold]{OwnerName}[/gold]을 처치 시, 빼앗긴 카드가 손으로 돌아옵니다.",
  "GRABBED.title": "붙잡힘",
  "GRAVITY_POWER.description": "이번 턴에 카드를 사용할 때마다, 모든 적에게 피해를 [blue]2[/blue] 줍니다.",
  "GRAVITY_POWER.smartDescription": "이번 턴에 카드를 사용할 때마다, 모든 적에게 피해를 [blue]{Amount}[/blue] 줍니다.",
  "GRAVITY_POWER.title": "중력",
  "GUARDED_POWER.description": "적에게 받는 피해가 [blue]50%[/blue] 감소합니다.",
  "GUARDED_POWER.smartDescription": "적에게 받는 피해가 [blue]{DamageDecrease:percentLess()}%[/blue] 감소합니다. [gold]{Applier.StringValue}[/gold](이)가 사망 시 제거됩니다.",
  "GUARDED_POWER.title": "보호됨",
  "HAILSTORM_POWER.description": "내 턴 종료 시 [gold]냉기[/gold]를 보유하고 있다면, 모든 적에게 피해를 [blue]6[/blue] 줍니다.",
  "HAILSTORM_POWER.smartDescription": "내 턴 종료 시 [gold]냉기[/gold]를 보유하고 있다면, 모든 적에게 피해를 [blue]{Amount}[/blue] 줍니다.",
  "HAILSTORM_POWER.title": "우박 폭풍",
  "HAMMER_TIME_POWER.description": "[gold]단조[/gold]할 때마다, 모든 아군이 [gold]단조[/gold]합니다.",
  "HAMMER_TIME_POWER.smartDescription": "[gold]단조[/gold]할 때마다, 모든 아군이 [gold]단조[/gold]합니다.",
  "HAMMER_TIME_POWER.title": "망치질 시간",
  "HANG_POWER.description": "모든 [gold]매달기[/gold] 카드가 이 적에게 가하는 피해량이 [blue]2[/blue]배로 증가합니다.",
  "HANG_POWER.smartDescription": "모든 [gold]매달기[/gold] 카드가 이 적에게 가하는 피해량이 [blue]{Amount}[/blue]배로 증가합니다.",
  "HANG_POWER.title": "매달기",
  "HARDENED_SHELL_POWER.description": "이 생물은 한 턴에 체력을 [blue]20[/blue] 이상 잃을 수 없습니다.",
  "HARDENED_SHELL_POWER.smartDescription": "[gold]{OwnerName}[/gold]는 한 턴에 체력을 [blue]{Amount}[/blue] 이상 잃을 수 없습니다.",
  "HARDENED_SHELL_POWER.title": "단단한 껍질",
  "HARD_TO_KILL_POWER.description": "[gold]갑각충[/gold]이 받는 모든 피해와 체력 손실이 [blue]9[/blue]로 감소합니다.",
  "HARD_TO_KILL_POWER.smartDescription": "[gold]{OwnerName}[/gold]이 받는 모든 피해와 체력 손실이 [blue]{Amount}[/blue]로 감소합니다.",
  "HARD_TO_KILL_POWER.title": "질긴 생존력",
  "HATCH_POWER.description": "X턴 후에 부화합니다.",
  "HATCH_POWER.smartDescription": "{Amount}턴 후에 부화합니다.",
  "HATCH_POWER.title": "부화",
  "HAUNT_POWER.description": "[gold]영혼[/gold]을 사용할 때마다, 무작위 적이 체력을 [blue]3[/blue] 잃습니다.",
  "HAUNT_POWER.smartDescription": "[gold]영혼[/gold]을 사용할 때마다, 무작위 적이 체력을 [blue]{Amount}[/blue] 잃습니다.",
  "HAUNT_POWER.title": "출몰",
  "HEATSINKS_POWER.description": "파워 카드를 사용할 때마다, 카드를 [blue]1[/blue]장 뽑습니다.",
  "HEATSINKS_POWER.smartDescription": "파워 카드를 사용할 때마다, 카드를 [blue]{Amount}[/blue]장 뽑습니다.",
  "HEATSINKS_POWER.title": "방열판",
  "HEIST_POWER.description": "사망 시, 빼앗은 모든 [gold]골드[/gold]를 반환합니다.",
  "HEIST_POWER.smartDescription": "사망 시, 빼앗은 모든 [gold]골드[/gold]를 반환합니다.",
  "HEIST_POWER.title": "강도",
  "HELLO_WORLD_POWER.description": "내 턴 시작 시, 무작위 일반 카드를 [blue]1[/blue]장 [gold]손[/gold]으로 가져옵니다.",
  "HELLO_WORLD_POWER.smartDescription": "내 턴 시작 시, 무작위 일반 카드를 [blue]{Amount}[/blue]장 [gold]손[/gold]으로 가져옵니다.",
  "HELLO_WORLD_POWER.title": "Hello World",
  "HELLRAISER_POWER.description": "이름에 \"타격\"이 포함된 카드를 뽑을 때마다, 무작위 적에게 사용합니다.",
  "HELLRAISER_POWER.infiniteAutoPlayCapReached": "충분하다.",
  "HELLRAISER_POWER.smartDescription": "이름에 \"타격\"이 포함된 카드를 뽑을 때마다, 무작위 적에게 사용합니다.",
  "HELLRAISER_POWER.title": "지옥검무",
  "HEX_POWER.description": "유령 기사가 살아있는 동안, 모든 카드에 [gold]휘발성[/gold]이 추가됩니다.",
  "HEX_POWER.title": "주술",
  "HIBERNATE_POWER.description": "이번 턴 동안, 내 [gold]냉기[/gold]가 모든 아군에게 [gold]방어도[/gold]를 제공합니다.",
  "HIBERNATE_POWER.smartDescription": "{Amount:choose(1):이번 턴 동안|다음 [blue]{}[/blue]턴 동안}, 내 [gold]냉기[/gold]가 모든 아군에게 [gold]방어도[/gold]를 제공합니다.",
  "HIBERNATE_POWER.title": "동면",
  "HIGH_VOLTAGE_POWER.description": "이 생물의 턴 종료 시, 대상이 [gold]힘[/gold]을 [blue]2[/blue] 얻습니다.",
  "HIGH_VOLTAGE_POWER.smartDescription": "[gold]{OwnerName}[/gold]의 턴 종료 시, 대상이 [gold]힘[/gold]을 [blue]{Amount}[/blue] 얻습니다.",
  "HIGH_VOLTAGE_POWER.title": "고전압",
  "ILLUSION_POWER.description": "사망 시, 다음 턴에 체력이 가득 찬 상태로 부활합니다.",
  "ILLUSION_POWER.smartDescription": "사망 시, 다음 턴에 체력이 가득 찬 상태로 부활합니다.",
  "ILLUSION_POWER.title": "환상",
  "IMBALANCED_POWER.description": "어떤 플레이어에 의해서든 이 생물의 공격이 완전히 막힌다면, 대상이 [gold]기절[/gold] 상태가 됩니다.",
  "IMBALANCED_POWER.smartDescription": "{IsMultiplayer:어떤 플레이어에 의해서든 |}[gold]{OwnerName}[/gold]의 공격이 완전히 막힌다면, 대상이 [gold]기절[/gold] 상태가 됩니다.",
  "IMBALANCED_POWER.title": "불균형",
  "IMITATION_LEARNING_POWER.description": "다른 플레이어가 파워 카드를 사용 시, 그 복사본을 사용합니다.",
  "IMITATION_LEARNING_POWER.smartDescription": "[gold]{TargetPlayer}[/gold](이)가 {Amount:choose(1):|다음 [blue]{}[/blue]번 }파워 카드를 사용 시, 그 복사본을 사용합니다.",
  "IMITATION_LEARNING_POWER.title": "모방 학습",
  "IMPROVEMENT_POWER.description": "전투 종료 시, 무작위 카드를 1장 [gold]강화[/gold]합니다.",
  "IMPROVEMENT_POWER.smartDescription": "전투 종료 시, 무작위 카드를 [blue]{Amount}[/blue]장 [gold]강화[/gold]합니다.",
  "IMPROVEMENT_POWER.title": "개선",
  "INFERNO_POWER.description": "내 턴 시작 시, 체력을 [blue]1[/blue] 잃습니다. 내 턴 동안 체력을 잃을 때마다, 모든 적에게 피해를 [blue]4[/blue] 줍니다.",
  "INFERNO_POWER.smartDescription": "내 턴 시작 시, 체력을 [blue]{SelfDamage}[/blue] 잃습니다. 내 턴 동안 체력을 잃을 때마다, 모든 적에게 피해를 [blue]{Amount}[/blue] 줍니다.",
  "INFERNO_POWER.title": "불바다",
  "INFESTED_POWER.description": "사망 시, 무언가를... 소환합니다.",
  "INFESTED_POWER.smartDescription": "사망 시, 무언가를... 소환합니다.",
  "INFESTED_POWER.title": "감염됨",
  "INFINITE_BLADES_POWER.description": "내 턴 시작 시, [gold]단도[/gold]를 1장 [gold]손[/gold]으로 가져옵니다.",
  "INFINITE_BLADES_POWER.smartDescription": "내 턴 시작 시, {Amount:choose(1):[gold]단도[/gold]를 1장|[gold]단도[/gold]를 [blue]{}[/blue]장} [gold]손[/gold]으로 가져옵니다.",
  "INFINITE_BLADES_POWER.title": "무한의 검날",
  "INKED.description": "이 생물이 공격으로 받는 피해가 [blue]2[/blue] 증가합니다.",
  "INKED.smartDescription": "이 생물이 공격으로 받는 피해가 [blue]{Amount}[/blue] 증가합니다.",
  "INKED.title": "잉크투성이",
  "INTANGIBLE_POWER.description": "이번 턴 동안 받는 모든 피해와 체력 손실이 [blue]1[/blue]로 감소합니다.",
  "INTANGIBLE_POWER.smartDescription": "받는 모든 피해와 체력 손실이 [blue]1[/blue]로 감소합니다. [blue]{Amount}[/blue]턴 동안 유지됩니다.",
  "INTANGIBLE_POWER.title": "불가침",
  "INTERCEPT_POWER.description": "다른 플레이어를 엄호하고 있습니다. 대상 아군이 받아야 하는 모든 공격의 목표를 자신으로 변경합니다.",
  "INTERCEPT_POWER.smartDescription": "[gold]{Covering}[/gold]을(를) 엄호하고 있습니다. 대상 아군이 받아야 하는 모든 공격의 목표를 자신으로 변경합니다.",
  "INTERCEPT_POWER.title": "가로막기",
  "ITERATION_POWER.description": "매 턴마다 처음으로 상태이상 카드를 뽑을 시, 추가로 카드를 뽑습니다.",
  "ITERATION_POWER.smartDescription": "매 턴마다 처음으로 상태이상 카드를 뽑을 시, 카드를 [blue]{Amount}[/blue]장 뽑습니다.",
  "ITERATION_POWER.title": "순회",
  "JUGGERNAUT_POWER.description": "[gold]방어도[/gold]를 얻을 때마다, 무작위 적에게 피해를 [blue]6[/blue] 줍니다.",
  "JUGGERNAUT_POWER.smartDescription": "[gold]방어도[/gold]를 얻을 때마다, 무작위 적에게 피해를 [blue]{Amount}[/blue] 줍니다.",
  "JUGGERNAUT_POWER.title": "절대적인 힘",
  "JUGGLING_POWER.description": "매 턴마다 세 번째로 사용하는 공격 카드의 복사본을 1장 [gold]손[/gold]으로 가져옵니다.",
  "JUGGLING_POWER.smartDescription": "매 턴마다 세 번째로 사용하는 공격 카드의 복사본을 [blue]{Amount}[/blue]장 [gold]손[/gold]으로 가져옵니다.",
  "JUGGLING_POWER.title": "저글링",
  "KNOCKDOWN_POWER.description": "이 생물이 이번 턴에 다른 플레이어로부터 받는 피해량이 [blue]{Amount}[/blue]배가 됩니다.",
  "KNOCKDOWN_POWER.remoteDescription": "[gold]{Applier}[/gold]로 인해 이 적에게 가하는 피해량이 [blue]{Amount}[/blue]배가 됩니다.",
  "KNOCKDOWN_POWER.smartDescription": "이 적이 이번 턴에 다른 아군으로부터 받는 피해량이 [blue]{Amount}[/blue]배가 됩니다.",
  "KNOCKDOWN_POWER.title": "때려눕히기",
  "LEADERSHIP_POWER.description": "다른 모든 아군이 가하는 피해량이 [blue]1[/blue] 증가합니다.",
  "LEADERSHIP_POWER.smartDescription": "다른 모든 아군이 가하는 피해량이 [blue]{Amount}[/blue] 증가합니다.",
  "LEADERSHIP_POWER.title": "통솔력",
  "LETHALITY_POWER.description": "매 턴마다 처음으로 사용하는 공격 카드의 피해량이 50% 증가합니다.",
  "LETHALITY_POWER.smartDescription": "매 턴마다 처음으로 사용하는 공격 카드의 피해량이 [blue]{Amount}%[/blue] 증가합니다.",
  "LETHALITY_POWER.title": "치사성",
  "LIGHTNING_ROD_POWER.description": "다음 [blue]2[/blue]턴 동안 턴 시작 시, [gold]전기[/gold]를 [blue]1[/blue]번 [gold]영창[/gold]합니다.",
  "LIGHTNING_ROD_POWER.smartDescription": "다음 {Amount:choose(1):턴 시작 시|[blue]{}[/blue]턴 동안 턴 시작 시}, [gold]전기[/gold]를 [blue]1[/blue]번 [gold]영창[/gold]합니다.",
  "LIGHTNING_ROD_POWER.title": "피뢰침",
  "LOOP_POWER.description": "내 턴 시작 시, 다음 구체의 지속 능력을 발동시킵니다.",
  "LOOP_POWER.smartDescription": "내 턴 시작 시, 다음 구체의 지속 능력을 [blue]{Amount}[/blue]번 발동시킵니다.",
  "LOOP_POWER.title": "반복",
  "MACHINE_LEARNING_POWER.description": "내 턴 시작 시, 카드를 추가로 [blue]1[/blue]장 뽑습니다.",
  "MACHINE_LEARNING_POWER.smartDescription": "내 턴 시작 시, 카드를 추가로 [blue]{Amount}[/blue]장 뽑습니다.",
  "MACHINE_LEARNING_POWER.title": "기계학습",
  "MAGIC_BOMB_POWER.description": "내 턴 종료 시 피해를 [blue]20[/blue] 받습니다. 이 효과는 마법 기사가 사망 시 사라집니다.",
  "MAGIC_BOMB_POWER.smartDescription": "내 턴 종료 시 피해를 [blue]{Amount}[/blue] 받습니다. 이 효과는 마법 기사가 사망 시 사라집니다.",
  "MAGIC_BOMB_POWER.title": "마법 폭탄",
  "MASTER_PLANNER_POWER.description": "스킬 카드를 사용 시, 그 카드가 [gold]교활[/gold]을 얻습니다.",
  "MASTER_PLANNER_POWER.title": "설계의 대가",
  "MAYHEM_POWER.description": "내 턴 시작 시, [gold]뽑을 카드 더미[/gold] 맨 위의 카드를 사용합니다.",
  "MAYHEM_POWER.smartDescription": "내 턴 시작 시, [gold]뽑을 카드 더미[/gold]{Amount:choose(1): 맨 위의 카드를| 맨 위에서부터 [blue]{}[/blue]장의 카드를} 사용합니다.",
  "MAYHEM_POWER.title": "대혼란",
  "MELANCHOLY_POWER.description": "[gold]종말[/gold]이 부여될 때마다, 추가로 [blue]2[/blue] 부여합니다.",
  "MELANCHOLY_POWER.smartDescription": "[gold]종말[/gold]이 부여될 때마다, 추가로 [blue]{Amount}[/blue] 부여합니다.",
  "MELANCHOLY_POWER.title": "비애",
  "MIND_ROT_POWER.description": "매 턴마다 카드를 [blue]1[/blue]장 적게 뽑습니다.",
  "MIND_ROT_POWER.smartDescription": "매 턴마다 카드를 [blue]{Amount}[/blue]장 적게 뽑습니다.",
  "MIND_ROT_POWER.title": "정신 오염",
  "MINION_POWER.description": "하수인들은 우두머리가 죽을 시 전투를 포기합니다.",
  "MINION_POWER.smartDescription": "하수인들은 우두머리가 죽을 시 전투를 포기합니다.",
  "MINION_POWER.title": "하수인",
  "MOCK_CLONE_CARDS_ON_PLAY_POWER.title": "가짜 사용 시 카드 복제",
  "MOCK_DO_NOT_SCALE_IN_MULTIPLAYER_POWER.title": "가짜 멀티플레이 스케일 미적용",
  "MOCK_EXTRA_TURN_POWER.title": "가짜 추가 턴",
  "MOCK_FREE_CARDS_POWER.title": "가짜 무료 카드",
  "MOCK_GAIN_BLOCK_ON_ATTACK_POWER.title": "가짜 공격 시 방어도 획득",
  "MOCK_INVINCIBLE_ON_DEATH_POWER.title": "가짜 죽음에 면역",
  "MOCK_MODIFY_ENERGY_COST_POWER.title": "가짜 에너지 비용 조정",
  "MOCK_MODIFY_STAR_COST_POWER.title": "가짜 별 비용 조정",
  "MOCK_PHASE_OBSERVER_POWER.title": "가짜 페이즈 관찰자",
  "MOCK_PREVENT_DEATH_POWER.title": "가짜 죽음 방지",
  "MOCK_REMOVE_DRAWN_CARDS_FROM_COMBAT_POWER.title": "가짜 전투 시 카드 뽑기 제거",
  "MOCK_RESET_COMBAT_ON_SHUFFLE_POWER.title": "가짜 섞을 시 전투 초기화",
  "MOCK_REVIVE_POWER.title": "가짜 부활",
  "MOCK_SCALE_IN_MULTIPLAYER_POWER.title": "가짜 멀티플레이 스케일 적용",
  "MOCK_TEMPORARY_STRENGTH_LOSS.title": "가짜 일시적인 힘 손실",
  "MOCK_UNHITTABLE_POWER.title": "가짜 적중 당하지 않음",
  "MONARCHS_GAZE_POWER.description": "적을 공격할 때마다, 대상 적이 이번 턴 동안 [gold]힘[/gold]을 [blue]1[/blue] 잃습니다.",
  "MONARCHS_GAZE_POWER.smartDescription": "적을 공격할 때마다, 대상 적이 이번 턴 동안 [gold]힘[/gold]을 [blue]{Amount}[/blue] 잃습니다.",
  "MONARCHS_GAZE_POWER.title": "군주의 시선",
  "MONOLOGUE_POWER.description": "이번 턴에 카드를 사용할 때마다, 이번 턴 동안 [gold]힘[/gold]을 [blue]1[/blue] 얻습니다.",
  "MONOLOGUE_POWER.smartDescription": "이번 턴에 카드를 사용할 때마다, 이번 턴 동안 [gold]힘[/gold]을 [blue]{StrengthPower}[/blue] 얻습니다.\n현재 [gold]힘[/gold]을 [blue]{StrengthApplied}[/blue] 얻은 상태입니다.",
  "MONOLOGUE_POWER.title": "독백",
  "NECRO_MASTERY_POWER.description": "[gold]골골이[/gold]가 체력을 잃을 때마다, 모든 적이 동일한 만큼의 체력을 잃습니다.",
  "NECRO_MASTERY_POWER.smartDescription": "[gold]골골이[/gold]가 체력을 잃을 때마다, 모든 적이 동일한 만큼의 체력을{Amount:choose(1):| [blue]{Amount}[/blue]번} 잃습니다.",
  "NECRO_MASTERY_POWER.title": "강령의 극의",
  "NEMESIS_POWER.description": "두 턴마다 턴 종료 시, [gold]불가침[/gold]을 [blue]1[/blue] 얻습니다.",
  "NEMESIS_POWER.smartDescription": "두 턴마다 턴 종료 시, [gold]불가침[/gold]을 [blue]1[/blue] 얻습니다.",
  "NEMESIS_POWER.title": "네메시스",
  "NEUROSURGE_POWER.description": "내 턴 시작 시, 자신에게 [gold]종말[/gold]을 [blue]3[/blue] 부여합니다.",
  "NEUROSURGE_POWER.smartDescription": "내 턴 시작 시, 자신에게 [gold]종말[/gold]을 [blue]{Amount}[/blue] 부여합니다.",
  "NEUROSURGE_POWER.title": "정신 폭주",
  "NIGHTMARE_POWER.description": "다음 턴에 선택한 카드를 [blue]3[/blue]장 [gold]손[/gold]으로 가져옵니다.",
  "NIGHTMARE_POWER.smartDescription": "다음 턴에 [gold]{Card}[/gold] {Amount:choose(1):1장을|[blue]{}[/blue]장을} [gold]손[/gold]으로 가져옵니다.",
  "NIGHTMARE_POWER.title": "악몽",
  "NOSTALGIA_POWER.description": "매 턴마다 처음으로 사용하는 공격이나 스킬 카드를 [gold]뽑을 카드 더미[/gold] 맨 위에 놓습니다.",
  "NOSTALGIA_POWER.smartDescription": "매 턴마다 처음으로 사용하는 {Amount:choose(1):공격이나 스킬 카드를|공격이나 스킬 카드 {}장을} [gold]뽑을 카드 더미[/gold] 맨 위에 놓습니다.",
  "NOSTALGIA_POWER.title": "향수",
  "NOXIOUS_FUMES_POWER.description": "내 턴 시작 시, 모든 적에게 [gold]중독[/gold]을 [blue]2[/blue] 부여합니다.",
  "NOXIOUS_FUMES_POWER.smartDescription": "내 턴 시작 시, 모든 적에게 [gold]중독[/gold]을 [blue]{Amount}[/blue] 부여합니다.",
  "NOXIOUS_FUMES_POWER.title": "유독 가스",
  "NO_BLOCK_POWER.description": "카드를 통해 [gold]방어도[/gold]를 얻을 수 없습니다.",
  "NO_BLOCK_POWER.smartDescription": "다음 {Amount:choose(1):[blue]{}[/blue]턴 동안|[blue]{}[/blue]턴 동안} 카드를 통해 [gold]방어도[/gold]를 얻을 수 없습니다.",
  "NO_BLOCK_POWER.title": "방어 불가",
  "NO_DRAW_POWER.description": "이번 턴에 더 이상 카드를 뽑을 수 없습니다.",
  "NO_DRAW_POWER.smartDescription": "이번 턴에 더 이상 카드를 뽑을 수 없습니다.",
  "NO_DRAW_POWER.title": "뽑기 불가",
  "NO_ENERGY_GAIN_POWER.description": "이번 턴에 추가로 {energyPrefix:energyIcons(1)}를 얻을 수 없습니다.",
  "NO_ENERGY_GAIN_POWER.smartDescription": "이번 턴에 추가로 {energyPrefix:energyIcons(1)}를 얻을 수 없습니다.",
  "NO_ENERGY_GAIN_POWER.title": "에너지 획득 불가",
  "NO_ESCAPE_POWER.description": "[blue]3[/blue]턴 종료 시, [gold]종말[/gold]을 [blue]50[/blue] 얻습니다.",
  "NO_ESCAPE_POWER.smartDescription": "{Amount:choose(1):이번 턴|[blue]{}[/blue]턴 후 턴} 종료 시, [gold]종말[/gold]을 [blue]{DoomPower}[/blue] 얻습니다.",
  "NO_ESCAPE_POWER.title": "도망칠 수 없다",
  "OBLIVION_POWER.description": "카드를 사용할 때마다, 이 적이 [gold]종말[/gold]을 [blue]1[/blue] 얻습니다.",
  "OBLIVION_POWER.remoteDescription": "[gold]{ApplierName}[/gold]가 카드를 사용할 때마다, 이 적이 [gold]종말[/gold]을 [blue]{Amount}[/blue] 얻습니다.",
  "OBLIVION_POWER.smartDescription": "카드를 사용할 때마다, 이 적이 [gold]종말[/gold]을 [blue]{Amount}[/blue] 얻습니다.",
  "OBLIVION_POWER.title": "망각",
  "ONE_FOR_ALL_POWER.description": "비용이 [blue]0[/blue] {energyPrefix:energyIcons(1)}인공격 카드의 피해량이 증가합니다.",
  "ONE_FOR_ALL_POWER.smartDescription": "비용이 [blue]0[/blue] {energyPrefix:energyIcons(1)}인공격 카드의 피해량이 [blue]{Amount}[/blue] 증가합니다.",
  "ONE_FOR_ALL_POWER.title": "모두를 위한 하나",
  "ONE_TWO_PUNCH_POWER.description": "이번 턴에 다음에 사용하는 공격 카드가 두 번 사용됩니다.",
  "ONE_TWO_PUNCH_POWER.smartDescription": "이번 턴에 다음에 사용하는 {Amount:choose(1):공격 카드가|공격 카드 [blue]{}[/blue]장이} 두 번 사용됩니다.",
  "ONE_TWO_PUNCH_POWER.title": "원투 펀치",
  "ORBIT_POWER.description": "에너지를 [blue]4[/blue] 소모할 때마다, 에너지를 얻습니다.",
  "ORBIT_POWER.smartDescription": "{Energy:energyIcons()}를 소모할 때마다, {Amount:energyIcons()}를 얻습니다.",
  "ORBIT_POWER.title": "궤도",
  "ORB_GENERATOR.description": "이 적은 [gold]구체[/gold]의 힘을 활용할 수 있습니다. [gold]구체[/gold]는 내 턴 종료 시 발동되며 이로운 효과와 해로운 효과의 영향을 받지 않습니다.",
  "ORB_GENERATOR.title": "구체 생성기",
  "OUTBREAK_POWER.description": "[gold]중독[/gold]을 부여할 때마다, 모든 적에게 피해를 줍니다.",
  "OUTBREAK_POWER.smartDescription": "[gold]중독[/gold]을 부여할 때마다, 모든 적에게 피해를 [blue]{Amount}[/blue] 줍니다.",
  "OUTBREAK_POWER.title": "발병",
  "PAGESTORM_POWER.description": "[gold]휘발성[/gold] 카드를 뽑을 때마다, 카드를 [blue]1[/blue]장 뽑습니다.",
  "PAGESTORM_POWER.smartDescription": "[gold]휘발성[/gold] 카드를 뽑을 때마다, 카드를 [blue]{Amount}[/blue]장 뽑습니다.",
  "PAGESTORM_POWER.title": "서류 폭풍",
  "PAINFUL_STABS_POWER.description": "내가 막히지 않은 공격 피해를 받을 때마다, [gold]버린 카드 더미[/gold]에 [gold]부상[/gold]을 [blue]1[/blue]장 섞어 넣습니다.",
  "PAINFUL_STABS_POWER.smartDescription": "내가 막히지 않은 공격 피해를 받을 때마다, [gold]버린 카드 더미[/gold]에 [gold]부상[/gold]을 [blue]{Amount}[/blue]장 섞어 넣습니다.",
  "PAINFUL_STABS_POWER.title": "고통스러운 찌르기",
  "PALE_BLUE_DOT_POWER.description": "한 턴에 카드를 특정 횟수 이상 사용했다면, 다음 턴 시작 시 카드를 추가로 뽑습니다.",
  "PALE_BLUE_DOT_POWER.smartDescription": "한 턴에 카드를 [blue]{CardPlay}[/blue]장 이상 사용했다면, 다음 턴 시작 시 카드를 추가로 [blue]{Amount}[/blue]장 뽑습니다.",
  "PALE_BLUE_DOT_POWER.title": "창백한 푸른 점",
  "PANACHE_POWER.description": "이번 턴에 카드를 [blue]5[/blue] 장 사용 시, 모든 적에게 피해를 줍니다.",
  "PANACHE_POWER.smartDescription": "이번 턴에 카드를 [blue]{CardsLeft}[/blue]장 이상 사용 시, 모든 적에게 피해를 [blue]{Amount}[/blue] 줍니다.",
  "PANACHE_POWER.title": "위풍당당",
  "PAPER_CUTS_POWER.description": "이 생물에게서 막히지 않은 공격 피해를 받을 때마다, [gold]최대 체력[/gold]을 [blue]1[/blue] 잃습니다.",
  "PAPER_CUTS_POWER.smartDescription": "[gold]{OwnerName}[/gold]에게서 막히지 않은 공격 피해를 받을 때마다, [gold]최대 체력[/gold]을 [blue]{Amount}[/blue] 잃습니다.",
  "PAPER_CUTS_POWER.title": "종이 베기",
  "PARRY_POWER.description": "[gold]군주의 칼날[/gold]을 사용 시 이제 [gold]방어도[/gold]를 얻습니다.",
  "PARRY_POWER.smartDescription": "[gold]군주의 칼날[/gold]을 사용 시 이제 [gold]방어도[/gold]를 [blue]{Amount}[/blue] 얻습니다.",
  "PARRY_POWER.title": "쳐내기",
  "PERSONAL_HIVE_POWER.description": "이 적이 공격 카드에 적중당할 때마다, [gold]뽑을 카드 더미[/gold]에 [gold]어지러움[/gold]을 추가합니다.",
  "PERSONAL_HIVE_POWER.smartDescription": "이 적이 공격 카드에 적중당할 때마다, [gold]뽑을 카드 더미[/gold]에 [gold]어지러움[/gold]을 [blue]{Amount}[/blue]장 추가합니다.",
  "PERSONAL_HIVE_POWER.title": "개인 군락",
  "PHANTOM_BLADES_POWER.description": "[gold]단도[/gold]가 [gold]보존[/gold]을 얻습니다.\n매 턴마다 처음으로 사용하는 [gold]단도[/gold]의 피해량이 [blue]9[/blue] 증가합니다.",
  "PHANTOM_BLADES_POWER.smartDescription": "[gold]단도[/gold]가 [gold]보존[/gold]을 얻습니다.\n매 턴마다 처음으로 사용하는 [gold]단도[/gold]의 피해량이 [blue]{Amount}[/blue] 증가합니다.",
  "PHANTOM_BLADES_POWER.title": "환영검",
  "PILLAR_OF_CREATION_POWER.description": "매 턴마다 카드를 처음으로 생성할 때마다, [gold]방어도[/gold]를 [blue]{Amount}[/blue] 얻습니다.",
  "PILLAR_OF_CREATION_POWER.smartDescription": "매 턴마다 카드를 처음으로 생성할 때마다, [gold]방어도[/gold]를 [blue]{Amount}[/blue] 얻습니다.",
  "PILLAR_OF_CREATION_POWER.title": "창조의 기둥",
  "PLATING_POWER.description": "내 턴 종료 시, [gold]방어도[/gold]를 획득합니다. [gold]판금[/gold]은 내 턴 시작 시 [blue]1[/blue] 감소합니다.",
  "PLATING_POWER.smartDescription": "내 턴 종료 시, [gold]방어도[/gold]를 [blue]{Amount}[/blue] 획득합니다. [gold]판금[/gold]은 내 턴 시작 시 [blue]{Decrement}[/blue] 감소합니다.",
  "PLATING_POWER.title": "판금",
  "PLOW_POWER.description": "이 생물의 체력이 처음으로 [blue]150[/blue] 이하로 떨어질 시, 대상이 [gold]기절[/gold] 상태가 됩니다.",
  "PLOW_POWER.smartDescription": "[gold]{OwnerName}[/gold]의 체력이 처음으로 [blue]{Amount}[/blue] 이하로 떨어질 시, 대상이 [gold]기절[/gold] 상태가 되고 모든 [gold]힘[/gold]을 잃습니다.",
  "PLOW_POWER.title": "갈아엎기",
  "POISON_POWER.description": "중독된 생물은 자신의 턴 시작 시 체력을 잃습니다. 매 턴마다 중독이 [blue]1[/blue] 감소합니다.",
  "POISON_POWER.smartDescription": "{OnPlayer:내 턴 시작 시|대상의 턴 시작 시} 체력을 [blue]{Amount}[/blue] 잃고, [gold]중독[/gold]이 [blue]1[/blue] 감소합니다.",
  "POISON_POWER.title": "중독",
  "POSSESS_SPEED_POWER.description": "처치 시, 빼앗은 모든 [gold]민첩[/gold]이 플레이어에게 돌아갑니다.",
  "POSSESS_SPEED_POWER.smartDescription": "처치 시, 빼앗은 모든 [gold]민첩[/gold]이 플레이어에게 돌아갑니다.",
  "POSSESS_SPEED_POWER.title": "속도 지배",
  "POSSESS_STRENGTH_POWER.description": "처치 시, 빼앗은 모든 [gold]힘[/gold]이 플레이어에게 돌아갑니다.",
  "POSSESS_STRENGTH_POWER.smartDescription": "처치 시, 빼앗은 모든 [gold]힘[/gold]이 플레이어에게 돌아갑니다.",
  "POSSESS_STRENGTH_POWER.title": "힘 지배",
  "PREP_TIME_POWER.description": "내 턴 시작 시, [gold]활력[/gold]을 [blue]4[/blue] 얻습니다.",
  "PREP_TIME_POWER.smartDescription": "내 턴 시작 시, [gold]활력[/gold]을 [blue]{Amount}[/blue] 얻습니다.",
  "PREP_TIME_POWER.title": "준비 시간",
  "PYRE_POWER.description": "매 턴 시작 시, [gold]에너지[/gold]를 [blue]1[/blue] 얻습니다.",
  "PYRE_POWER.smartDescription": "매 턴 시작 시, {Amount:energyIcons()}를 얻습니다.",
  "PYRE_POWER.title": "불의 심장",
  "RADIANCE_POWER.description": "다음 턴에 추가로 [gold]에너지[/gold]를 얻습니다.",
  "RADIANCE_POWER.smartDescription": "{Amount:choose(1):다음 턴에|다음 [blue]{}[/blue]턴 동안} 추가로 {Energy:energyIcons()}를 얻습니다.",
  "RADIANCE_POWER.title": "광휘",
  "RAGE_POWER.description": "이번 턴에 공격 카드를 사용할 때마다, [gold]방어도[/gold]를 [blue]3[/blue] 얻습니다.",
  "RAGE_POWER.smartDescription": "이번 턴에 공격 카드를 사용할 때마다, [gold]방어도[/gold]를 [blue]{Amount}[/blue] 얻습니다.",
  "RAGE_POWER.title": "격노",
  "RAMPART_POWER.description": "플레이어의 턴 시작 시, 포탑 사수가 [gold]방어도[/gold]를 [blue]25[/blue] 얻습니다.",
  "RAMPART_POWER.smartDescription": "플레이어의 턴 시작 시, 포탑 사수가 [gold]방어도[/gold]를 [blue]{Amount}[/blue] 얻습니다.",
  "RAMPART_POWER.title": "방벽",
  "RAVENOUS_POWER.description": "적이 사망 시, 시체 민달팽이가 그 적을 즉시 먹어치우며 [gold]기절[/gold] 상태가 되고, [gold]힘[/gold]을 [blue]1[/blue] 얻습니다.",
  "RAVENOUS_POWER.smartDescription": "적이 사망 시, 시체 민달팽이가 그 적을 즉시 먹어치우며 [gold]기절[/gold] 상태가 되고, [gold]힘[/gold]을 [blue]{Amount}[/blue] 얻습니다.",
  "RAVENOUS_POWER.title": "굶주림",
  "READ_THE_BONES_POWER.description": "[gold]소환[/gold]할 때마다, 카드를 1장 뽑습니다.",
  "READ_THE_BONES_POWER.smartDescription": "[gold]소환[/gold]할 때마다, 카드를 [blue]{Amount}[/blue]장 뽑습니다.",
  "READ_THE_BONES_POWER.title": "뼈 읽기",
  "REAPER_FORM_POWER.description": "공격 카드로 피해를 줄 때마다, 그와 동일한 만큼의 [gold]종말[/gold]을 부여합니다.",
  "REAPER_FORM_POWER.smartDescription": "공격 카드로 피해를 줄 때마다, {Amount:choose(1):피해량과 동일한|피해량의 [blue]{}[/blue]배} 만큼의 [gold]종말[/gold]을 부여합니다.",
  "REAPER_FORM_POWER.title": "사신의 형상",
  "REATTACH_POWER.description": "다른 부위가 살아있다면, [blue]2[/blue]턴 후에 [blue]25[/blue]의 체력으로 부활합니다.",
  "REATTACH_POWER.smartDescription": "다른 부위가 살아있다면, [blue]2[/blue]턴 후에 [blue]{Amount}[/blue]의 체력으로 부활합니다.",
  "REATTACH_POWER.title": "재부착",
  "REBOUND_POWER.description": "이번 턴에 다음으로 사용하는 카드를 [gold]뽑을 카드 더미[/gold] 맨 위에 놓습니다.",
  "REBOUND_POWER.smartDescription": "이번 턴에 다음으로 사용하는 {Amount:choose(1):카드를|카드 [blue]{}[/blue]장을} [gold]뽑을 카드 더미[/gold] 맨 위에 놓습니다.",
  "REBOUND_POWER.title": "되돌리기",
  "REFLECTIVE_FORTRESS_POWER.description": "공격을 완전히 [gold]방어[/gold] 할 때마다, 방어한 피해량을 공격자에게 반사합니다.",
  "REFLECTIVE_FORTRESS_POWER.smartDescription": "공격을 완전히 [gold]방어[/gold] 할 때마다, 방어한 {Amount:choose(1):피해량을|피해량을 [blue]{}[/blue]배로} 공격자에게 반사합니다.",
  "REFLECTIVE_FORTRESS_POWER.title": "반사하는 요새",
  "REFLECT_POWER.description": "막은 공격 피해가 공격한 적에게 반사됩니다.",
  "REFLECT_POWER.smartDescription": "다음 [blue]{Amount}[/blue]턴 동안 막은 피해가 공격한 적에게 반사됩니다.",
  "REFLECT_POWER.title": "반사",
  "REGEN_POWER.description": "[gold]재생[/gold]은 내 턴 종료 시 체력을 회복시킵니다. 매 턴마다 [gold]재생[/gold]이 [blue]1[/blue] 감소합니다.",
  "REGEN_POWER.smartDescription": "내 턴 종료 시, 체력을 [blue]{Amount}[/blue] 회복하고, [gold]재생[/gold]이 [blue]1[/blue] 감소합니다.",
  "REGEN_POWER.title": "재생",
  "RESERVES_POWER.description": "카드 사용을 위한 [gold]에너지[/gold]가 부족한 경우, [gold]에너지[/gold]마다 2{singleStarIcon}이 대신 사용됩니다.",
  "RESERVES_POWER.smartDescription": "카드 사용을 위한 {energyPrefix:energyIcons(1)}가 부족한 경우, {energyPrefix:energyIcons(1)}마다 2{singleStarIcon}이 대신 사용됩니다.",
  "RESERVES_POWER.title": "비축물",
  "RESTORE_DEXTERITY.description": "대상의 턴 종료 시, [gold]민첩[/gold]을 [blue]9[/blue] 얻습니다.",
  "RESTORE_DEXTERITY.smartDescription": "대상의 종료 시, [gold]민첩[/gold]을 [blue]{Amount}[/blue] 얻습니다.",
  "RESTORE_DEXTERITY.title": "민첩 회복",
  "RESTORE_FOCUS.description": "대상의 턴 종료 시, [gold]밀집[/gold]을 [blue]9[/blue] 얻습니다.",
  "RESTORE_FOCUS.smartDescription": "대상의 턴 종료 시, [gold]밀집[/gold]을 [blue]{Amount}[/blue] 얻습니다.",
  "RESTORE_FOCUS.title": "밀집 회복",
  "RETAIN_HAND_POWER.description": "다음 [blue]2[/blue]턴 동안, [gold]손[/gold]에 있는 카드들을 [gold]보존[/gold]합니다.",
  "RETAIN_HAND_POWER.smartDescription": "{Amount:choose(1):이번 턴에|다음 [blue]{}[/blue]턴 동안,} [gold]손[/gold]에 있는 카드들을 [gold]보존[/gold]합니다.",
  "RETAIN_HAND_POWER.title": "손패 보존",
  "RINGING_POWER.description": "이번 턴에는 카드를 [blue]1[/blue]장만 낼 수 있습니다.",
  "RINGING_POWER.smartDescription": "이번 턴에는 카드를 [blue]{Amount}[/blue]장만 낼 수 있습니다.",
  "RINGING_POWER.title": "공명",
  "RITUAL_POWER.description": "내 턴 종료 시, [gold]힘[/gold]을 얻습니다.",
  "RITUAL_POWER.smartDescription": "{OnPlayer:내 턴|대상의 턴} 종료 시, [gold]힘[/gold]을 [blue]{Amount}[/blue] 얻습니다.",
  "RITUAL_POWER.title": "의식",
  "ROLLING_BOULDER_POWER.description": "내 턴 시작 시, 모든 적에게 피해를 [blue]5[/blue] 주고 이 효과의 피해량이 [blue]5[/blue] 증가합니다.",
  "ROLLING_BOULDER_POWER.smartDescription": "내 턴 시작 시, 모든 적에게 피해를 [blue]{Amount}[/blue] 주고 이 효과의 피해량이 [blue]{Damage}[/blue] 증가합니다.",
  "ROLLING_BOULDER_POWER.title": "굴러가는 바위",
  "ROYALTIES_POWER.description": "전투 종료 시, [gold]골드[/gold]를 [blue]25[/blue] 얻습니다.",
  "ROYALTIES_POWER.smartDescription": "전투 종료 시, [gold]골드[/gold]를 [blue]{Amount}[/blue] 얻습니다.",
  "ROYALTIES_POWER.title": "로열티",
  "RUPTURE_POWER.description": "내 턴 동안 체력을 잃을 때마다, [gold]힘[/gold]을 [blue]1[/blue] 얻습니다.",
  "RUPTURE_POWER.smartDescription": "내 턴 동안 체력을 잃을 때마다, [gold]힘[/gold]을 [blue]{Amount}[/blue] 얻습니다.",
  "RUPTURE_POWER.title": "파열",
  "SANDPIT_POWER.description": "탐이 사용하는 파워입니다.",
  "SANDPIT_POWER.smartDescription": "{Amount:choose(1):[gold]탐[/gold]의 턴이 시작될 시|[blue]{}[/blue]턴 후에}, 당신은 탐에게 먹혀 사망할 것입니다.",
  "SANDPIT_POWER.title": "모래 구덩이",
  "SEEKING_EDGE_POWER.description": "[gold]군주의 칼날[/gold]이 이제 모든 적을 대상으로 합니다.",
  "SEEKING_EDGE_POWER.smartDescription": "[gold]군주의 칼날[/gold]이 이제 모든 적을 대상으로 합니다.",
  "SEEKING_EDGE_POWER.title": "날 세우기",
  "SELF_FORMING_CLAY_POWER.description": "다음 턴에 [gold]방어도[/gold]를 [blue]3[/blue] 얻습니다.",
  "SELF_FORMING_CLAY_POWER.smartDescription": "다음 턴에 [gold]방어도[/gold]를 [blue]{Amount}[/blue] 얻습니다.",
  "SELF_FORMING_CLAY_POWER.title": "자가 형성 점토",
  "SENTRY_MODE_POWER.description": "내 턴 시작 시, [gold]훑어보기[/gold]를 [blue]1[/blue]장 [gold]손[/gold]으로 가져옵니다.",
  "SENTRY_MODE_POWER.smartDescription": "내 턴 시작 시, [gold]훑어보기[/gold]를 [blue]{Amount}[/blue]장 [gold]손[/gold]으로 가져옵니다.",
  "SENTRY_MODE_POWER.title": "경계 태세",
  "SERPENT_FORM_POWER.description": "카드를 사용할 때마다, 무작위 적에게 피해를 [blue]4[/blue] 줍니다.",
  "SERPENT_FORM_POWER.smartDescription": "카드를 사용할 때마다, 무작위 적에게 피해를 [blue]{Amount}[/blue] 줍니다.",
  "SERPENT_FORM_POWER.title": "구렁이의 형상",
  "SHADOWMELD_POWER.description": "이번 턴 동안 얻는 [gold]방어도[/gold]가 2배가 됩니다.",
  "SHADOWMELD_POWER.smartDescription": "이번 턴 동안 얻는 [gold]방어도[/gold]가{Amount:choose(1):| [blue]{}[/blue]번} 2배가 됩니다.",
  "SHADOWMELD_POWER.title": "그림자 은신",
  "SHADOW_STEP_POWER.description": "다음 턴에, 공격 카드의 피해량이 2배가 됩니다.",
  "SHADOW_STEP_POWER.smartDescription": "{Amount:choose(1):다음 턴에|다음 턴부터 [blue]{}[/blue]턴 동안}, 공격 카드의 피해량이 2배가 됩니다.",
  "SHADOW_STEP_POWER.title": "그림자 걸음",
  "SHARP_EDGE_POWER.description": "[gold]단도[/gold]를 생성할 때마다, 그 단도를 [gold]강화[/gold]합니다.",
  "SHARP_EDGE_POWER.smartDescription": "[gold]단도[/gold]를 생성할 때마다, 그 단도를 [gold]강화[/gold]합니다.",
  "SHARP_EDGE_POWER.title": "예리한 날",
  "SHRIEK_POWER.description": "이 생물의 체력이 처음으로 [blue]50%[/blue] 이하로 떨어질 시, 대상이 [gold]기절[/gold] 상태가 됩니다.",
  "SHRIEK_POWER.smartDescription": "[gold]{OwnerName}[/gold]의 체력이 처음으로 [blue]{Amount}[/blue] 이하로 떨어질 시, 대상이 [gold]기절[/gold] 상태가 됩니다.",
  "SHRIEK_POWER.title": "괴성",
  "SHRINK_POWER.description": "다음 3턴 동안 이 생물이 가하는 공격의 피해량이 [blue]30%[/blue] 감소합니다.",
  "SHRINK_POWER.smartDescription": "{Amount:cond:==1?다음 턴에 |>1?다음 [blue]{}[/blue] 턴 동안, |}{ApplierName.StringValue:cond:{}가 살아있는 동안, 내가|[gold]{OwnerName}가[/gold]} 가하는 공격의 피해량이 [blue]{DamageDecrease}%[/blue] 감소합니다.",
  "SHRINK_POWER.title": "압축",
  "SHROUD_POWER.description": "[gold]종말[/gold]을 부여할 때마다, [gold]방어도[/gold]를 [blue]3[/blue] 얻습니다.",
  "SHROUD_POWER.smartDescription": "[gold]종말[/gold]을 부여할 때마다, [gold]방어도[/gold]를 [blue]{Amount}[/blue] 얻습니다.",
  "SHROUD_POWER.title": "수의",
  "SIC_EM_POWER.description": "이번 턴에 [gold]골골이[/gold]가 이 적을 공격할 때마다, [gold]소환[/gold] [blue]3[/blue].",
  "SIC_EM_POWER.smartDescription": "이번 턴에 [gold]골골이[/gold]가 이 적을 공격할 때마다, [gold]소환[/gold] [blue]{Amount}[/blue].",
  "SIC_EM_POWER.title": "덮쳐!",
  "SIGNAL_BOOST_POWER.description": "다음에 사용하는 파워 카드가 1번 추가로 사용됩니다.",
  "SIGNAL_BOOST_POWER.smartDescription": "다음에 사용하는 파워 {Amount:choose(1):카드가|카드 [blue]{}[/blue]장이} 1번 추가로 사용됩니다.",
  "SIGNAL_BOOST_POWER.title": "신호 증폭",
  "SKITTISH_POWER.description": "매 턴마다 이 생물이 처음으로 공격을 받을 때, 대상이 [gold]방어도[/gold]를 [blue]1[/blue] 얻습니다.",
  "SKITTISH_POWER.smartDescription": "매 턴마다 [gold]{OwnerName}[/gold]가 처음으로 공격을 받을 때, 대상이 [gold]방어도[/gold]를 [blue]{Amount}[/blue] 얻습니다.",
  "SKITTISH_POWER.title": "겁쟁이",
  "SLEIGHT_OF_FLESH_POWER.description": "적에게 해로운 효과를 부여할 때마다, 대상 적이 피해를 [blue]13[/blue] 받습니다.",
  "SLEIGHT_OF_FLESH_POWER.smartDescription": "적에게 해로운 효과를 부여할 때마다, 대상 적이 피해를 [blue]{Amount}[/blue] 받습니다.",
  "SLEIGHT_OF_FLESH_POWER.title": "살점 재주",
  "SLIPPERY_POWER.description": "이 생물이 다음에 체력을 잃을 시, [blue]1[/blue]만 잃습니다.",
  "SLIPPERY_POWER.smartDescription": "[gold]{OwnerName}[/gold]이 {Amount:choose(1):다음에|다음 [blue]{}[/blue]번} 체력을 잃을 시, [blue]1[/blue]만 잃습니다.",
  "SLIPPERY_POWER.title": "미끈거림",
  "SLOTH_POWER.description": "매 턴마다 카드를 최대 [blue]3[/blue]장까지만 사용할 수 있습니다.",
  "SLOTH_POWER.smartDescription": "매 턴마다 카드를 최대 [blue]{Amount}[/blue]장까지만 사용할 수 있습니다.",
  "SLOTH_POWER.title": "나태",
  "SLOW_POWER.description": "카드를 사용할 때마다, 이번 턴 동안 대상 적이 공격 카드를 통해 받는 피해량이 [blue]10%[/blue] 증가합니다.",
  "SLOW_POWER.smartDescription": "카드를 사용할 때마다, 이번 턴 동안 {OnPlayer:내가|대상 적이} 공격 카드를 통해 받는 피해량이 [blue]10%[/blue] 증가합니다.{Amount:choose(1):| (피해량이 [blue]{Amount}%[/blue] 증가합니다)}",
  "SLOW_POWER.title": "둔화",
  "SLUMBER_POWER.description": "턴이 경과하거나 체력을 잃는 것이 3번 발생 시, 깨어납니다.",
  "SLUMBER_POWER.smartDescription": "턴이 경과하거나 체력을 잃는 것이 [blue]{Amount}[/blue]번 발생 시, 깨어납니다.",
  "SLUMBER_POWER.title": "숙면",
  "SMOGGY_POWER.description": "한 턴에 스킬 카드를 [blue]1[/blue]장만 사용할 수 있습니다.",
  "SMOGGY_POWER.smartDescription": "한 턴에 스킬 카드를 [blue]{Amount}[/blue]장만 사용할 수 있습니다.",
  "SMOGGY_POWER.title": "연무",
  "SMOKESTACK_POWER.description": "상태이상 카드를 생성할 때마다, 모든 적에게 피해를 줍니다.",
  "SMOKESTACK_POWER.smartDescription": "상태이상 카드를 생성할 때마다, 모든 적에게 피해를 [blue]{Amount}[/blue] 줍니다.",
  "SMOKESTACK_POWER.title": "배기 장치",
  "SNEAKY_POWER.description": "다른 플레이어가 적을 공격할 때마다, [gold]방어도[/gold]를 얻습니다.",
  "SNEAKY_POWER.smartDescription": "다른 플레이어가 적을 공격할 때마다, [gold]방어도[/gold]를 [blue]{Amount}[/blue] 얻습니다.",
  "SNEAKY_POWER.title": "비열함",
  "SOAR_POWER.description": "착지 전까지 공격으로 받는 피해량이 [gold]50%[/gold] 감소합니다.",
  "SOAR_POWER.smartDescription": "착지 전까지 공격으로 받는 피해량이 [blue]{DamageDecrease}%[/blue] 감소합니다.",
  "SOAR_POWER.title": "날아오르기",
  "SOULBOUND_POWER.description": "{ApplierName}(이)가 [gold]영혼[/gold]을 생성할 때마다, [gold]뽑을 카드 더미[/gold]에 [gold]영혼[/gold]을 1장 추가합니다.",
  "SOULBOUND_POWER.smartDescription": "{ApplierName}(이)가 [gold]영혼[/gold]을 생성할 때마다, [gold]뽑을 카드 더미[/gold]에 [gold]영혼[/gold]을 {Amount}장 추가합니다.",
  "SOULBOUND_POWER.title": "영혼 결속",
  "SOUL_WITHER.description": "영혼 결합체가 막히지 않은 공격 피해를 9번 준 후, 당신에게 피해를 999 줍니다.",
  "SOUL_WITHER.smartDescription": "영혼 결합체가 막히지 않은 공격 피해를 [blue]{Amount}[/blue]번 준 후, 당신에게 피해를 [blue]{Damage}[/blue] 줍니다.",
  "SOUL_WITHER.title": "시드는 영혼",
  "SOW_POWER.description": "이번 턴에 [gold]손[/gold]에 있는 무작위 카드를 [blue]1[/blue]장 [gold]보존[/gold]합니다.",
  "SOW_POWER.smartDescription": "이번 턴에 [gold]손[/gold]에 있는 무작위 카드를 [blue]{Amount}[/blue]장 [gold]보존[/gold]합니다.",
  "SOW_POWER.title": "씨뿌리기",
  "SPECTRUM_SHIFT_POWER.description": "내 턴 시작 시, 무작위 무색 카드를 [blue]1[/blue]장 [gold]손[/gold]으로 가져옵니다.",
  "SPECTRUM_SHIFT_POWER.smartDescription": "내 턴 시작 시, 무작위 무색 카드를 [blue]{Amount}[/blue]장 [gold]손[/gold]으로 가져옵니다.",
  "SPECTRUM_SHIFT_POWER.title": "스펙트럼 이동",
  "SPEEDSTER_POWER.description": "내 턴 동안 카드를 뽑을 때마다, 모든 적에게 피해를 [blue]1[/blue] 줍니다.",
  "SPEEDSTER_POWER.smartDescription": "내 턴 동안 카드를 뽑을 때마다, 모든 적에게 피해를 [blue]{Amount}[/blue] 줍니다.",
  "SPEEDSTER_POWER.title": "스피드스터",
  "SPINNER_POWER.description": "내 턴 시작 시, [gold]유리[/gold]를 [blue]1[/blue]번 [gold]영창[/gold]합니다.",
  "SPINNER_POWER.smartDescription": "내 턴 시작 시, [gold]유리[/gold]를 [blue]{Amount}[/blue]번 [gold]영창[/gold]합니다.",
  "SPINNER_POWER.title": "스피너",
  "SPIRIT_OF_ASH_POWER.description": "[gold]휘발성[/gold] 카드를 사용할 때마다, [gold]방어도[/gold]를 [blue]4[/blue] 얻습니다.",
  "SPIRIT_OF_ASH_POWER.smartDescription": "[gold]휘발성[/gold] 카드를 사용할 때마다, [gold]방어도[/gold]를 [blue]{Amount}[/blue] 얻습니다.",
  "SPIRIT_OF_ASH_POWER.title": "잿빛 혼령",
  "STAMPEDE_POWER.description": "내 턴 종료 시, [gold]손[/gold]에 있는 무작위 공격 카드 [blue]1[/blue]장을 무작위 적에게 사용합니다.",
  "STAMPEDE_POWER.smartDescription": "내 턴 종료 시, [gold]손[/gold]에 있는 무작위 공격 카드 [blue]{Amount}[/blue]장을 무작위 적에게 사용합니다.",
  "STAMPEDE_POWER.title": "쇄도",
  "STAR_NEXT_TURN_POWER.description": "다음 턴에 {singleStarIcon}을 1 얻습니다.",
  "STAR_NEXT_TURN_POWER.smartDescription": "다음 턴에 {singleStarIcon}을 [blue]{Amount}[/blue] 얻습니다.",
  "STAR_NEXT_TURN_POWER.title": "다음 턴 별",
  "STEAM_ERUPTION_POWER.description": "사망한다면, 다음 내 턴 종료 시 피해를 줍니다.",
  "STEAM_ERUPTION_POWER.smartDescription": "사망한다면, 다음 내 턴 종료 시 피해를 [blue]{Amount}[/blue] 줍니다.",
  "STEAM_ERUPTION_POWER.title": "증기 분출",
  "STOCK_POWER.description": "사망 시, 그 장소에 새로운 잘라봇을 소환합니다.",
  "STOCK_POWER.title": "재고",
  "STORM_POWER.description": "파워 카드를 사용할 때마다, [gold]전기[/gold]를 [blue]1[/blue]번 [gold]영창[/gold]합니다.",
  "STORM_POWER.smartDescription": "파워 카드를 사용할 때마다, [gold]전기[/gold]를 [blue]{Amount}[/blue]번 [gold]영창[/gold]합니다.",
  "STORM_POWER.title": "폭풍",
  "STRANGLE_POWER.description": "이번 턴에 카드를 사용할 때마다, 이 적이 체력을 [blue]2[/blue] 잃습니다.",
  "STRANGLE_POWER.remoteDescription": "[gold]{ApplierName}[/gold]가 이번 턴에 카드를 사용할 때마다, 이 적이 체력을 [blue]{Amount}[/blue] 잃습니다.",
  "STRANGLE_POWER.smartDescription": "이번 턴에 카드를 사용할 때마다, 이 적이 체력을 [blue]{Amount}[/blue] 잃습니다.",
  "STRANGLE_POWER.title": "목 조르기",
  "STRATAGEM_POWER.description": "[gold]뽑을 카드 더미[/gold]를 섞을 때마다, 카드를 [blue]1[/blue]장 선택해 [gold]손[/gold]으로 가져옵니다.",
  "STRATAGEM_POWER.selectionScreenPrompt": "손으로 가져올 카드를{Amount:choose(1):| {}장} 선택하세요.",
  "STRATAGEM_POWER.smartDescription": "[gold]뽑을 카드 더미[/gold]를 섞을 때마다, 카드를 [blue]{Amount}[/blue]장 선택해 [gold]손[/gold]으로 가져옵니다.",
  "STRATAGEM_POWER.title": "책략",
  "STRENGTH_POWER.description": "힘은 공격 카드의 피해량을 증가시킵니다.",
  "STRENGTH_POWER.smartDescription": "공격 카드의 피해량이 [blue]{Amount:abs()}[/blue] {Amount:cond:<0?감소합니다|증가합니다}.",
  "STRENGTH_POWER.title": "힘",
  "SUBROUTINE_POWER.description": "파워 카드를 사용할 때마다, {energyPrefix:energyIcons(1)}를 얻습니다.",
  "SUBROUTINE_POWER.smartDescription": "파워 카드를 사용할 때마다, {Amount:energyIcons()}를 얻습니다.",
  "SUBROUTINE_POWER.title": "서브루틴",
  "SUCK_POWER.description": "이 생물이 막히지 않은 공격 피해를 줄 때마다, 대상이 [gold]힘[/gold]을 [blue]1[/blue] 얻습니다.",
  "SUCK_POWER.smartDescription": "[gold]{OwnerName}[/gold]가 막히지 않은 공격 피해를 줄 때마다, 대상이 [gold]힘[/gold]을 [blue]{Amount}[/blue] 얻습니다.",
  "SUCK_POWER.title": "흡입",
  "SUMMON_NEXT_TURN_POWER.description": "다음 턴 시작 시, [gold]소환[/gold] [blue]2[/blue].",
  "SUMMON_NEXT_TURN_POWER.smartDescription": "다음 턴 시작 시, [gold]소환[/gold] [blue]{Amount}[/blue].",
  "SUMMON_NEXT_TURN_POWER.title": "다음 턴 소환",
  "SURPRISE_POWER.description": "이 생물은 뭔가 이상해 보입니다...",
  "SURPRISE_POWER.smartDescription": "이 생물은 뭔가 이상해 보입니다...",
  "SURPRISE_POWER.title": "서프라이즈",
  "SURROUNDED_POWER.description": "뒤에서의 공격으로 받는 피해가 [blue]50%[/blue] 증가합니다. 목표를 지정하는 카드나 포션을 사용해 향하는 방향을 변경할 수 있습니다.",
  "SURROUNDED_POWER.title": "포위됨",
  "SWIPE_POWER.description": "이 적을 처치 시, 빼앗긴 카드를 돌려받습니다.",
  "SWIPE_POWER.title": "슬쩍하기",
  "SWORD_SAGE_POWER.description": "[gold]군주의 칼날[/gold]이 [gold]재사용[/gold]을 [blue]1[/blue] 얻습니다.",
  "SWORD_SAGE_POWER.smartDescription": "[gold]군주의 칼날[/gold]이 [gold]재사용[/gold]을 [blue]{Amount}[/blue] 얻습니다.",
  "SWORD_SAGE_POWER.title": "검성",
  "TAG_TEAM_POWER.description": "다른 플레이어가 다음에 대상 적에게 사용하는 공격이 {Amount:choose(1):1번 추가로 사용됩니다.|[blue]{}[/blue]번 추가로 사용됩니다}.",
  "TAG_TEAM_POWER.remoteDescription": "[gold]{ApplierName}[/gold]에 의해 다른 플레이어가 다음에 대상 적에게 사용하는 공격 카드가 1번 추가로 사용됩니다.",
  "TAG_TEAM_POWER.smartDescription": "다른 플레이어가 다음에 대상 적에게 사용하는 공격 카드가 1번 추가로 사용됩니다.",
  "TAG_TEAM_POWER.title": "태그 팀",
  "TAINTED_POWER.description": "이번 턴 동안 공격을 통해 받는 피해량이 증가합니다.",
  "TAINTED_POWER.smartDescription": "이번 턴 동안 공격을 통해 받는 피해량이 [blue]{Amount}[/blue] 증가합니다.",
  "TAINTED_POWER.title": "훼손됨",
  "TANGLED_POWER.description": "이번 턴 동안 공격 카드의 [gold]에너지[/gold] 비용이 [blue]1[/blue] 증가합니다.",
  "TANGLED_POWER.smartDescription": "{Amount:choose(1):이번 턴 동안|다음 {}턴 동안} 공격 카드의 비용이 {Amount:energyIcons()} 증가합니다.",
  "TANGLED_POWER.title": "뒤얽힘",
  "TANK_POWER.description": "적에게 받는 피해가 [blue]50%[/blue] 증가합니다. 아군이 적에게 받는 피해가 [blue]50%[/blue] 감소합니다.",
  "TANK_POWER.smartDescription": "적에게 받는 피해가 [blue]{DamageIncrease:percentMore()}%[/blue] 증가합니다. 아군이 적에게 받는 피해가 [blue]{DamageDecrease:percentLess()}%[/blue] 감소합니다.",
  "TANK_POWER.title": "탱커",
  "TAUNT_POWER.description": "적이 당신을 공격 시, 공격한 적에게 [gold]취약[/gold]을 [blue]1[/blue] 부여합니다.",
  "TAUNT_POWER.smartDescription": "적이 당신을 공격 시, 공격한 적에게 [gold]취약[/gold]을 [blue]{Amount}[/blue] 부여합니다.",
  "TAUNT_POWER.title": "도발",
  "TEMPORARY_DEXTERITY_DOWN.description": "이번 턴이 끝나기 전까지 [gold]민첩[/gold]을 잃습니다.",
  "TEMPORARY_DEXTERITY_DOWN.smartDescription": "이번 턴이 끝나기 전까지 [gold]민첩[/gold]을 [blue]{Amount}[/blue] 잃습니다.",
  "TEMPORARY_DEXTERITY_POWER.description": "이번 턴이 끝나기 전까지 [gold]민첩[/gold]을 얻습니다.",
  "TEMPORARY_DEXTERITY_POWER.smartDescription": "이번 턴이 끝나기 전까지 [gold]민첩[/gold]을 [blue]{Amount}[/blue] 얻습니다.",
  "TEMPORARY_FOCUS_DOWN.description": "이번 턴이 끝나기 전까지 [gold]밀집[/gold]을 잃습니다.",
  "TEMPORARY_FOCUS_DOWN.smartDescription": "이번 턴이 끝나기 전까지 [gold]밀집[/gold]을 [blue]{Amount}[/blue] 잃습니다.",
  "TEMPORARY_FOCUS_POWER.description": "이번 턴이 끝나기 전까지 [gold]밀집[/gold]을 얻습니다.",
  "TEMPORARY_FOCUS_POWER.smartDescription": "이번 턴이 끝나기 전까지 [gold]밀집[/gold]을 [blue]{Amount}[/blue] 얻습니다.",
  "TEMPORARY_STRENGTH_DOWN.description": "이번 턴이 끝나기 전까지 [gold]힘[/gold]을 잃습니다.",
  "TEMPORARY_STRENGTH_DOWN.smartDescription": "이번 턴이 끝나기 전까지 [gold]힘[/gold]을 [blue]{Amount}[/blue] 잃습니다.",
  "TEMPORARY_STRENGTH_POWER.description": "이번 턴이 끝나기 전까지 [gold]힘[/gold]을 얻습니다.",
  "TEMPORARY_STRENGTH_POWER.smartDescription": "이번 턴이 끝나기 전까지 [gold]힘[/gold]을 [blue]{Amount}[/blue] 얻습니다.",
  "TENDER_POWER.description": "카드를 사용할 때마다, 이번 턴 동안 [gold]힘[/gold]을 [blue]1[/blue] 잃고 [gold]민첩[/gold]을 [blue]1[/blue] 잃습니다.",
  "TENDER_POWER.smartDescription": "카드를 사용할 때마다, 이번 턴 동안 [gold]힘[/gold]을 [blue]{Amount}[/blue] 잃고 [gold]민첩[/gold]을 [blue]{Amount}[/blue] 잃습니다.",
  "TENDER_POWER.title": "연약함",
  "TERRITORIAL_POWER.description": "이 생물의 턴 종료 시, 대상이 [gold]힘[/gold]을 [blue]1[/blue] 얻습니다.",
  "TERRITORIAL_POWER.smartDescription": "[gold]{OwnerName}'s[/gold]의 턴 종료 시, 대상이 [gold]힘[/gold]을 [blue]{Amount}[/blue] 얻습니다.",
  "TERRITORIAL_POWER.title": "영역 동물",
  "TEZCATARAS_BLIGHT.description": "이번 턴 종료 시, [gold]힘[/gold]을 [blue]1[/blue] 잃습니다.",
  "TEZCATARAS_BLIGHT.smartDescription": "이번 턴 종료 시, [gold]힘[/gold]을 [blue]{Amount}[/blue] 잃습니다.",
  "TEZCATARAS_BLIGHT.title": "테즈카타라의 역병",
  "THE_BOMB_POWER.description": "[blue]3[/blue]턴 후 턴 종료 시, 모든 적에게 피해를 [blue]40[/blue] 줍니다.",
  "THE_BOMB_POWER.smartDescription": "{Amount:choose(1):이번 턴|[blue]{}[/blue]턴 후 턴} 종료 시, 모든 적에게 피해를 [blue]{Damage}[/blue] 줍니다.",
  "THE_BOMB_POWER.title": "폭탄",
  "THE_GAMBIT_POWER.description": "이번 전투 동안 막히지 않은 공격 피해를 받는다면, 사망합니다.",
  "THE_GAMBIT_POWER.smartDescription": "이번 전투 동안 막히지 않은 공격 피해를 받는다면, 사망합니다.",
  "THE_GAMBIT_POWER.title": "포석",
  "THE_HUNT_POWER.description": "전투 종료 시 카드 보상을 추가로 [blue]1[/blue]번 얻습니다.",
  "THE_HUNT_POWER.smartDescription": "전투 종료 시 카드 보상을 추가로 [blue]{Amount}[/blue]번 얻습니다.",
  "THE_HUNT_POWER.title": "사냥",
  "THE_SEALED_THRONE_POWER.description": "카드를 사용할 때마다, {singleStarIcon}을 얻습니다.",
  "THE_SEALED_THRONE_POWER.smartDescription": "카드를 사용할 때마다, {Amount:starIcons()}을 얻습니다.",
  "THE_SEALED_THRONE_POWER.title": "봉인된 왕좌",
  "THIEVERY_POWER.description": "공격 시 [gold]골드[/gold]를 빼앗습니다.",
  "THIEVERY_POWER.smartDescription": "공격 시 [gold]골드[/gold]를 [blue]{Amount}[/blue] 빼앗습니다.",
  "THIEVERY_POWER.title": "도둑질",
  "THORNS_POWER.description": "공격에 적중 시, 공격자에게 피해를 줍니다.",
  "THORNS_POWER.smartDescription": "공격에 적중 시, 공격자에게 피해를 [blue]{Amount}[/blue] 줍니다.",
  "THORNS_POWER.title": "가시",
  "THUNDER_POWER.description": "[gold]전기[/gold]를 [gold]발현[/gold]할 때마다, 적중한 적에게 피해를 [blue]8[/blue] 줍니다.",
  "THUNDER_POWER.smartDescription": "[gold]전기[/gold]를 [gold]발현[/gold]할 때마다, 적중한 적에게 피해를 [blue]{Amount}[/blue] 줍니다.",
  "THUNDER_POWER.title": "벼락",
  "TOOLS_OF_THE_TRADE_POWER.description": "내 턴 시작 시, 카드를 [blue]1[/blue]장 뽑고 카드를 [blue]1[/blue]장 버립니다.",
  "TOOLS_OF_THE_TRADE_POWER.smartDescription": "내 턴 시작 시, 카드를 [blue]{Amount}[/blue]장 뽑고 카드를 [blue]{Amount}[/blue]장 버립니다.",
  "TOOLS_OF_THE_TRADE_POWER.title": "작업 도구",
  "TORIC_TOUGHNESS_POWER.description": "다음 [blue]2[/blue]턴 동안, 턴 시작 시 [gold]방어도[/gold]를 [blue]5[/blue] 얻습니다.",
  "TORIC_TOUGHNESS_POWER.smartDescription": "다음 [blue]{Amount}[/blue]턴 동안, 턴 시작 시 [gold]방어도[/gold]를 [blue]{Block:diff()}[/blue] 얻습니다.",
  "TORIC_TOUGHNESS_POWER.title": "고리형 강인함",
  "TORN.description": "매 턴마다 카드를 [blue]1[/blue]장 덜 뽑습니다.",
  "TORN.smartDescription": "매 턴마다 카드를 [blue]{Amount}[/blue]장 덜 뽑습니다.",
  "TORN.title": "찢겨나감",
  "TRACKING_POWER.description": "[gold]약화[/gold] 상태의 적이 공격 카드로 받는 피해가 [blue]50%[/blue] 증가합니다.",
  "TRACKING_POWER.smartDescription": "[gold]약화[/gold] 상태의 적이 공격 카드로 받는 피해가 [blue]{Amount}%[/blue] 증가합니다.",
  "TRACKING_POWER.title": "추적",
  "TRASH_TO_TREASURE_POWER.description": "상태이상 카드를 생성할 때마다, 무작위 구체를 [blue]1[/blue]개 [gold]영창[/gold]합니다.",
  "TRASH_TO_TREASURE_POWER.smartDescription": "상태이상 카드를 생성할 때마다, 무작위 구체를 {Amount:choose(1):[blue]{}[/blue]개|[blue]{}[/blue]개} [gold]영창[/gold]합니다.",
  "TRASH_TO_TREASURE_POWER.title": "고철을 보물로",
  "TYRANNY_POWER.description": "내 턴 시작 시, 카드를 1장 뽑고 [gold]손[/gold]에 있는 카드를 1장 [gold]소멸[/gold]시킵니다.",
  "TYRANNY_POWER.smartDescription": "내 턴 시작 시, 카드를 {Amount:choose(1):[blue]{}[/blue]장|[blue]{}[/blue]장} 뽑고 [gold]손[/gold]에 있는 카드를 {Amount:choose(1):[blue]{}[/blue]장|[blue]{}[/blue]장} [gold]소멸[/gold]시킵니다.",
  "TYRANNY_POWER.title": "독재",
  "UNDERWORLD_POWER.description": "다른 플레이어가 이번 턴 동안 공격 피해를 가할 때마다, 그와 동일한 만큼의 [gold]종말[/gold]을 부여합니다.",
  "UNDERWORLD_POWER.smartDescription": "다른 플레이어가 이번 턴 동안 공격 피해를 가할 때마다, {Amount:choose(1):피해량과 동일한|피해량의 [blue]{}[/blue]배} 만큼의 [gold]종말[/gold]을 부여합니다.",
  "UNDERWORLD_POWER.title": "지하세계",
  "UNMOVABLE_POWER.description": "매 턴마다 처음으로 카드를 통해 얻는 [gold]방어도[/gold]가 2배가 됩니다.",
  "UNMOVABLE_POWER.smartDescription": "매 턴마다 {Amount:choose(1):처음으로|[blue]{}[/blue]번,} 카드를 통해 얻는 [gold]방어도[/gold]가 2배가 됩니다.",
  "UNMOVABLE_POWER.title": "요지부동",
  "UNSTABLE.description": "공격 카드를 사용할 때마다, 대상 적이 체력을 [blue]5[/blue] 잃습니다.",
  "UNSTABLE.smartDescription": "공격 카드를 사용할 때마다, {OnPlayer:|대상 적이 }체력을 [blue]{Amount}[/blue] 잃습니다.",
  "UNSTABLE.title": "불안정",
  "UNSTEADY.description": "철퇴 기사의 체력이 [blue]50%[/blue] 이하로 떨어질 시, [gold]기절[/gold] 상태가 됩니다.",
  "UNSTEADY.smartDescription": "철퇴 기사의 체력이 [blue]{HealthLimit}%[/blue] 이하로 떨어질 시, 대상이 [gold]기절[/gold] 상태가 됩니다.",
  "UNSTEADY.title": "휘청거림",
  "VEILPIERCER_POWER.description": "다음에 사용하는 [gold]휘발성 카드[/gold]의 비용이 [blue]0[/blue]이 됩니다.",
  "VEILPIERCER_POWER.smartDescription": "다음에 사용하는 [gold]휘발성[/gold] 카드 [blue]{Amount}[/blue]장의 비용이 [blue]0[/blue]이 됩니다.",
  "VEILPIERCER_POWER.title": "장막 관통자",
  "VICIOUS_POWER.description": "[gold]취약[/gold]을 부여할 때마다, 카드를 [blue]1[/blue]장 뽑습니다.",
  "VICIOUS_POWER.smartDescription": "[gold]취약[/gold]을 부여할 때마다, 카드를 [blue]{Amount}[/blue]장 뽑습니다.",
  "VICIOUS_POWER.title": "포악함",
  "VIGOR_POWER.description": "다음 공격의 피해량이 증가합니다.",
  "VIGOR_POWER.smartDescription": "{OnPlayer:|[gold]{OwnerName}[/gold]의 }다음 공격의 피해량이 [blue]{Amount}[/blue] 증가합니다.",
  "VIGOR_POWER.title": "활력",
  "VISUAL_ONLY.description": "비주얼 온리",
  "VISUAL_ONLY.title": "비주얼 온리",
  "VITAL_SPARK_POWER.description": "모든 [gold]스킬[/gold] 카드에 [gold]훼손됨[/gold]이 [blue]2[/blue] 추가됩니다.",
  "VITAL_SPARK_POWER.smartDescription": "모든 [gold]스킬[/gold] 카드에 [gold]훼손됨[/gold]이 [blue]{Amount}[/blue] 추가됩니다.",
  "VITAL_SPARK_POWER.title": "생명의 불꽃",
  "VOID_FORM_POWER.description": "매 턴마다 처음으로 사용하는 카드 [blue]2[/blue]장이 비용 없이 사용됩니다.",
  "VOID_FORM_POWER.smartDescription": "매 턴마다 처음으로 사용하는 {Amount:choose(1):카드가|카드 [blue]{}[/blue]장이} 비용 없이 사용됩니다.",
  "VOID_FORM_POWER.title": "공허의 형상",
  "VULNERABLE_POWER.description": "취약 상태인 생물은 공격 카드를 통해 받는 피해량이 [blue]50%[/blue] 증가합니다.",
  "VULNERABLE_POWER.smartDescription": "[blue]{Amount}[/blue]턴 동안 공격 카드를 통해 받는 피해량이 [blue]{DamageIncrease:percentMore()}%[/blue] 증가합니다.",
  "VULNERABLE_POWER.title": "취약",
  "WASTE_AWAY_POWER.description": "매 턴마다 얻는 [gold]에너지[/gold]가 [blue]1[/blue] 감소합니다.",
  "WASTE_AWAY_POWER.smartDescription": "매 턴마다 얻는 {energyPrefix:energyIcons(1)}가 [blue]{Amount}[/blue] 감소합니다.",
  "WASTE_AWAY_POWER.title": "쇠퇴",
  "WEAK_POWER.description": "약화 상태인 생물의 공격은 가하는 피해량이 [blue]25%[/blue] 감소합니다.",
  "WEAK_POWER.smartDescription": "[blue]{Amount}[/blue]턴 동안 공격이 가하는 피해량이 [blue]25%[/blue] 감소합니다.",
  "WEAK_POWER.title": "약화",
  "WELL_LAID_PLANS_POWER.description": "내 턴 종료 시, 더 이상 [gold]손[/gold]에 있는 카드를 버리지 않습니다.",
  "WELL_LAID_PLANS_POWER.smartDescription": "내 턴 종료 시, 더 이상 [gold]손[/gold]에 있는 카드를 버리지 않습니다.",
  "WELL_LAID_PLANS_POWER.title": "괜찮은 전략",
  "WINGED_JUMP_POWER.description": "내 턴 시작 시, 모든 적에게 [gold]취약[/gold]을 [blue]1[/blue] 부여합니다.",
  "WINGED_JUMP_POWER.smartDescription": "내 턴 시작 시, 모든 적에게 [gold]취약[/gold]을 [blue]{Amount}[/blue] 부여합니다.",
  "WINGED_JUMP_POWER.title": "비행 점프",
  "WITHERING_PRESENCE_POWER.description": "카드를 [blue]6[/blue]장 사용할 때마다, [gold]시듦[/gold]을 1장 [gold]손[/gold]으로 가져옵니다.",
  "WITHERING_PRESENCE_POWER.smartDescription": "카드를 [blue]6[/blue]장 사용할 때마다, [gold]시듦[/gold]을 1장 [gold]손[/gold]으로 가져옵니다.",
  "WITHERING_PRESENCE_POWER.title": "시들어가는 존재",
  "WRAITH_FORM_POWER.description": "내 턴 시작 시, [gold]민첩[/gold]을 [blue]1[/blue] 잃습니다.",
  "WRAITH_FORM_POWER.smartDescription": "내 턴 시작 시, [gold]민첩[/gold]을 [blue]{Amount}[/blue] 잃습니다.",
  "WRAITH_FORM_POWER.title": "유령의 형상"
}
